[
    {
        "content": "<p>The small avatar takes some time to load in the user popover which results in a blank area for a few secs. Should we do something about it?</p>",
        "id": 197821,
        "sender_full_name": "Vishnu KS",
        "timestamp": 1494362951
    },
    {
        "content": "<p>I think a simple solution is to show the popover only when the smaller image is loaded.</p>",
        "id": 197825,
        "sender_full_name": "Vishnu KS",
        "timestamp": 1494363115
    },
    {
        "content": "<p>Ahh, is this when clicking in the right sidebar?</p>",
        "id": 197826,
        "sender_full_name": "Tim Abbott",
        "timestamp": 1494363157
    },
    {
        "content": "<p>Yeah. Right sidebar or the sender name in message.</p>",
        "id": 197827,
        "sender_full_name": "Vishnu KS",
        "timestamp": 1494363174
    },
    {
        "content": "<p>I think only right sidebar.  In the message feed, we're guaranteed to have the small avatar already fetched from the server, but that's not true in the right sidebar.</p>",
        "id": 197828,
        "sender_full_name": "Tim Abbott",
        "timestamp": 1494363202
    },
    {
        "content": "<p>But I am facing delay in loading of images by clicking the sender name too.</p>",
        "id": 197835,
        "sender_full_name": "Vishnu KS",
        "timestamp": 1494363355
    },
    {
        "content": "<p>Hmm, not sure why that would be.  If the browser already has the image in cache, loading the image should be instant</p>",
        "id": 197838,
        "sender_full_name": "Tim Abbott",
        "timestamp": 1494363393
    },
    {
        "content": "<p>And I certainly can only reproduce using the right sidebar</p>",
        "id": 197840,
        "sender_full_name": "Tim Abbott",
        "timestamp": 1494363416
    },
    {
        "content": "<p>Ahh, can you check your JS console <span class=\"user-mention\" data-user-email=\"yo@vishnuks.com\" data-user-id=\"52\">@Vishnu Ks</span>?  I have a few 503s from gravatar on the larger-size avatar requests</p>",
        "id": 197847,
        "sender_full_name": "Tim Abbott",
        "timestamp": 1494363549
    },
    {
        "content": "<p>after trying a bunch of times</p>",
        "id": 197848,
        "sender_full_name": "Tim Abbott",
        "timestamp": 1494363554
    },
    {
        "content": "<p>hmm. I am not getting any 503s.</p>",
        "id": 197862,
        "sender_full_name": "Vishnu KS",
        "timestamp": 1494363857
    }
]