[
    {
        "content": "<p>I have made changes to this <a href=\"https://github.com/zulip/zulip/pull/21606\">pull request</a>. Please can it be reviewed ? <span class=\"user-mention silent\" data-user-id=\"5140\">Aman Agrawal (amanagr)</span>  <span class=\"user-mention silent\" data-user-id=\"19257\">Alya Abbott</span> <span class=\"user-mention silent\" data-user-id=\"7\">Tim Abbott</span></p>",
        "id": 1357110,
        "sender_full_name": "Kanu Mike Chibundu",
        "timestamp": 1648730580
    },
    {
        "content": "<p><span class=\"user-mention\" data-user-id=\"23647\">@Kanu Mike Chibundu</span> Thanks for working on the issue! Please don't post in this stream unless we need to discuss a design. Just leaving a comment on GitHub when your PR is ready for review is great.</p>",
        "id": 1357503,
        "sender_full_name": "Alya Abbott",
        "timestamp": 1648755940
    }
]