[
    {
        "content": "<p>That \"globe\" icon doesn't look great to me:</p>\n<ul>\n<li>It's hard to make out at that size. I'm not sure I would figure out it was meant to be a globe if I didn't know.</li>\n<li>It's trying to look like an actual view of a globe, which necessarily means it's a particular part of the world. (Basically centered on North America, it looks like.)</li>\n</ul>\n<p>Can we use a grid-style globe instead?</p>",
        "id": 1306188,
        "sender_full_name": "Greg Price",
        "timestamp": 1641582251
    },
    {
        "content": "<p>Ha, I guess Material's answer is that a grid-style globe means \"language\", and the icon for \"public\" is... basically the Western Hemisphere: <a href=\"/user_uploads/2/40/DwwMz2Sjb3FmnyqkrRK0X_JY/image.png\">image.png</a> <br>\n<a href=\"https://fonts.google.com/icons?selected=Material+Icons&amp;icon.query=globe\">https://fonts.google.com/icons?selected=Material+Icons&amp;icon.query=globe</a></p>\n<div class=\"message_inline_image\"><a href=\"/user_uploads/2/40/DwwMz2Sjb3FmnyqkrRK0X_JY/image.png\" title=\"image.png\"><img src=\"/user_uploads/2/40/DwwMz2Sjb3FmnyqkrRK0X_JY/image.png\"></a></div>",
        "id": 1306189,
        "sender_full_name": "Greg Price",
        "timestamp": 1641582321
    },
    {
        "content": "<p>Though then also it reuses the Western Hemisphere globe, plus other small icons, for \"Travel Explore\" and for \"Vpn Lock\": <a href=\"/user_uploads/2/34/KWm_Z9MXY7KlYUqYOuPRI0Ez/image.png\">image.png</a></p>\n<div class=\"message_inline_image\"><a href=\"/user_uploads/2/34/KWm_Z9MXY7KlYUqYOuPRI0Ez/image.png\" title=\"image.png\"><img src=\"/user_uploads/2/34/KWm_Z9MXY7KlYUqYOuPRI0Ez/image.png\"></a></div>",
        "id": 1306190,
        "sender_full_name": "Greg Price",
        "timestamp": 1641582392
    },
    {
        "content": "<p>I think if we want a map-like globe icon, Material's is at least more legible than the one in those draft screenshots. Also I feel like not being centered blatantly right on North America is an improvement.</p>\n<p>I'd also be happy to see a grid-style globe; in this context I don't think it's at risk of looking like it means \"choose your language\".</p>",
        "id": 1306192,
        "sender_full_name": "Greg Price",
        "timestamp": 1641582700
    },
    {
        "content": "<p>I guess the globe discussion is somewhat separate from this particular PR, unless we think it's specifically a deal-breaker for whether or not to use a globe in that banner. We should settle on  consistent iconography throughout:</p>\n<p><a href=\"/user_uploads/2/b6/LVmDGSPGKpSF4aV4z-ZfOEca/Screen-Shot-2022-01-07-at-11.22.12-AM.png\">Screen-Shot-2022-01-07-at-11.22.12-AM.png</a></p>\n<div class=\"message_inline_image\"><a href=\"/user_uploads/2/b6/LVmDGSPGKpSF4aV4z-ZfOEca/Screen-Shot-2022-01-07-at-11.22.12-AM.png\" title=\"Screen-Shot-2022-01-07-at-11.22.12-AM.png\"><img src=\"/user_uploads/2/b6/LVmDGSPGKpSF4aV4z-ZfOEca/Screen-Shot-2022-01-07-at-11.22.12-AM.png\"></a></div>",
        "id": 1306199,
        "sender_full_name": "Alya Abbott",
        "timestamp": 1641583451
    },
    {
        "content": "<p>I agree that it's nice that the Material Design globe is less focused on North America. The language connotation makes me worry about using a grid-style globe, though it looks like we currently don't use that icon in the language settings.</p>",
        "id": 1306201,
        "sender_full_name": "Alya Abbott",
        "timestamp": 1641583738
    },
    {
        "content": "<p>Yeah, agreed it should be consistent. If we're already using that globe in the sidebar, then I don't think it's any worse in that banner than there.</p>",
        "id": 1306213,
        "sender_full_name": "Greg Price",
        "timestamp": 1641585384
    },
    {
        "content": "<p>I think the globe might be a little worse in this spot just because of the blue font color from the link label styling, but yeah, I agree with that conclusion.</p>",
        "id": 1306465,
        "sender_full_name": "Tim Abbott",
        "timestamp": 1641599485
    },
    {
        "content": "<p>This topic was moved here from <a class=\"stream-topic\" data-stream-id=\"9\" href=\"/#narrow/stream/9-issues/topic/missing.20hash.20before.20stream.20name\">#issues &gt; missing hash before stream name</a> by <span class=\"user-mention silent\" data-user-id=\"19257\">Alya Abbott</span></p>",
        "id": 1306593,
        "sender_full_name": "Notification Bot",
        "timestamp": 1641604178
    },
    {
        "content": "<p>I moved this part of the above topic so that we can discuss what icon to use for world-public streams, separately from a particular place where that icon is being used.</p>",
        "id": 1306594,
        "sender_full_name": "Alya Abbott",
        "timestamp": 1641604240
    },
    {
        "content": "<p>How about <a href=\"/user_uploads/2/91/Op200bT3gykgMdFq9iW5CvdM/image.png\">image.png</a></p>\n<div class=\"message_inline_image\"><a href=\"/user_uploads/2/91/Op200bT3gykgMdFq9iW5CvdM/image.png\" title=\"image.png\"><img src=\"/user_uploads/2/91/Op200bT3gykgMdFq9iW5CvdM/image.png\"></a></div>",
        "id": 1306614,
        "sender_full_name": "Vlad Korobov",
        "timestamp": 1641607133
    },
    {
        "content": "<p><a href=\"https://feathericons.com/\">https://feathericons.com/</a></p>",
        "id": 1306615,
        "sender_full_name": "Vlad Korobov",
        "timestamp": 1641607144
    },
    {
        "content": "<p>this icon set is already in use on mobile as far as I know</p>",
        "id": 1306616,
        "sender_full_name": "Vlad Korobov",
        "timestamp": 1641607156
    },
    {
        "content": "<p>It can be bolder too <a href=\"/user_uploads/2/a3/Cu_QYu2pGrA4Pd9qksg19hjG/image.png\">image.png</a></p>\n<div class=\"message_inline_image\"><a href=\"/user_uploads/2/a3/Cu_QYu2pGrA4Pd9qksg19hjG/image.png\" title=\"image.png\"><img src=\"/user_uploads/2/a3/Cu_QYu2pGrA4Pd9qksg19hjG/image.png\"></a></div>",
        "id": 1306617,
        "sender_full_name": "Vlad Korobov",
        "timestamp": 1641607178
    },
    {
        "content": "<p>Yeah, that's a bit visually simpler of a grid-style globe than the one Material has, and that might be best for using it real small, like we do with these stream icons.</p>",
        "id": 1306630,
        "sender_full_name": "Greg Price",
        "timestamp": 1641608318
    },
    {
        "content": "<p>Between those two Feather variations the less-bold is the one I'd try first; the bolder one's lines might blur together when it's small.</p>",
        "id": 1306631,
        "sender_full_name": "Greg Price",
        "timestamp": 1641608357
    },
    {
        "content": "<p>Should I try using grid-style globe for compose box and banner box stream privacy decoration in these PRs ?</p>\n<ol>\n<li><a href=\"https://github.com/zulip/zulip/pull/20588\">compose: Add stream privacy decorations compose box. #20588</a></li>\n<li><a href=\"https://github.com/zulip/zulip/pull/20562\">compose: Add stream privacy decorations in banner box. #20562</a></li>\n</ol>",
        "id": 1306680,
        "sender_full_name": "Shivam Deotarse",
        "timestamp": 1641614427
    },
    {
        "content": "<p><span class=\"user-mention\" data-user-id=\"22454\">@Shivam Deotarse</span> this needs to be a separate PR, actually. Can you replace all the <code>fa-globe</code> icons with <a href=\"https://feathericons.com/?query=globe\">globe icon vlad mentioned</a>? Place the svg in <code>static/assets/icons</code> and use <code>zulip-icon zulip-icon-globe</code> as class to use the icon and post some screenshots?</p>",
        "id": 1307292,
        "sender_full_name": "Aman (amanagr)",
        "timestamp": 1641788913
    },
    {
        "content": "<p><span class=\"user-mention silent\" data-user-id=\"5140\">Aman Agrawal (amanagr)</span> <a href=\"#narrow/stream/101-design/topic/globe.20icon.20for.20world-public.20streams/near/1307292\">said</a>:</p>\n<blockquote>\n<p><span class=\"user-mention silent\" data-user-id=\"22454\">Shivam Deotarse</span> this needs to be a separate PR, actually. Can you replace all the <code>fa-globe</code> icons with <a href=\"https://feathericons.com/?query=globe\">globe icon vlad mentioned</a>? Place the svg in <code>static/assets/icons</code> and use <code>zulip-icon zulip-icon-globe</code> as class to use the icon and post some screenshots?</p>\n</blockquote>\n<p>I have replaced fa fa-globe with zulip-icon zulip-icon-globe and also added globe.svg to static/assets/icons. But, still new icon is not visible in place of old globe icon.<br>\nDo I have to make more changes <span class=\"user-mention\" data-user-id=\"5140\">@Aman Agrawal (amanagr)</span> ?</p>",
        "id": 1308055,
        "sender_full_name": "Shivam Deotarse",
        "timestamp": 1641900393
    },
    {
        "content": "<p><a href=\"https://feathericons.com/?query=globe\">New globe icon</a> is looking like this -<br>\n<a href=\"/user_uploads/2/e7/aiStfrDaKJkmFJb1LsSB7YxI/image.png\">image.png</a></p>\n<div class=\"message_inline_image\"><a href=\"/user_uploads/2/e7/aiStfrDaKJkmFJb1LsSB7YxI/image.png\" title=\"image.png\"><img src=\"/user_uploads/2/e7/aiStfrDaKJkmFJb1LsSB7YxI/image.png\"></a></div>",
        "id": 1308698,
        "sender_full_name": "Shivam Deotarse",
        "timestamp": 1641966443
    },
    {
        "content": "<p>Hmm, that doesn't look like the right icon at all -- it doesn't look like the screenshots <span class=\"user-mention silent\" data-user-id=\"22433\">Vlad Korobov</span> showed above, and it doesn't look much like a globe. Is it perhaps some other icon?</p>",
        "id": 1308702,
        "sender_full_name": "Greg Price",
        "timestamp": 1641967354
    },
    {
        "content": "<p>I think there is an issue with svg file</p>",
        "id": 1308704,
        "sender_full_name": "Vlad Korobov",
        "timestamp": 1641967456
    },
    {
        "content": "<p>something like this had happened somehow <a href=\"/user_uploads/2/8b/ZYYeZFermt5DrhWmKMd3IOb2/image.png\">image.png</a></p>\n<div class=\"message_inline_image\"><a href=\"/user_uploads/2/8b/ZYYeZFermt5DrhWmKMd3IOb2/image.png\" title=\"image.png\"><img src=\"/user_uploads/2/8b/ZYYeZFermt5DrhWmKMd3IOb2/image.png\"></a></div>",
        "id": 1308706,
        "sender_full_name": "Vlad Korobov",
        "timestamp": 1641967552
    },
    {
        "content": "<p><span class=\"user-mention silent\" data-user-id=\"22433\">Vlad Korobov</span> <a href=\"#narrow/stream/101-design/topic/globe.20icon.20for.20world-public.20streams/near/1306614\">said</a>:</p>\n<blockquote>\n<p>How about <a href=\"/user_uploads/2/91/Op200bT3gykgMdFq9iW5CvdM/image.png\">image.png</a></p>\n</blockquote>\n<p>I have used same globe.svg as mentioned above but, color is getting filled instead of applying color to icon outline only.</p>",
        "id": 1308709,
        "sender_full_name": "Shivam Deotarse",
        "timestamp": 1641968002
    },
    {
        "content": "<p>I'll try that in browser tomorrow</p>",
        "id": 1308711,
        "sender_full_name": "Vlad Korobov",
        "timestamp": 1641968129
    },
    {
        "content": "<p><span class=\"user-mention silent\" data-user-id=\"22454\">Shivam Deotarse</span> <a href=\"#narrow/stream/101-design/topic/globe.20icon.20for.20world-public.20streams/near/1308709\">said</a>:</p>\n<blockquote>\n<p><span class=\"user-mention silent\" data-user-id=\"22433\">Vlad Korobov</span> <a href=\"#narrow/stream/101-design/topic/globe.20icon.20for.20world-public.20streams/near/1306614\">said</a>:</p>\n<blockquote>\n<p>How about <a href=\"/user_uploads/2/91/Op200bT3gykgMdFq9iW5CvdM/image.png\">image.png</a></p>\n</blockquote>\n<p>I have used same globe.svg as mentioned above but, color is getting filled instead of applying color to icon outline only.</p>\n</blockquote>\n<p><span class=\"user-mention\" data-user-id=\"22454\">@Shivam Deotarse</span> is there a PR with this change that I could pull and look at?</p>",
        "id": 1308716,
        "sender_full_name": "Yash RE",
        "timestamp": 1641968493
    },
    {
        "content": "<p><span class=\"user-mention silent\" data-user-id=\"5140\">Aman Agrawal (amanagr)</span> <a href=\"#narrow/stream/101-design/topic/globe.20icon.20for.20world-public.20streams/near/1307292\">said</a>:</p>\n<blockquote>\n<p><span class=\"user-mention silent\" data-user-id=\"22454\">Shivam Deotarse</span> this needs to be a separate PR, actually. Can you replace all the <code>fa-globe</code> icons with <a href=\"https://feathericons.com/?query=globe\">globe icon vlad mentioned</a>? Place the svg in <code>static/assets/icons</code> and use <code>zulip-icon zulip-icon-globe</code> as class to use the icon and post some screenshots?</p>\n</blockquote>\n<p><span class=\"user-mention\" data-user-id=\"9808\">@Yash RE</span>  Actually I have followed above instructions on my local environment and have not created any PR.</p>",
        "id": 1308718,
        "sender_full_name": "Shivam Deotarse",
        "timestamp": 1641968982
    },
    {
        "content": "<p>I see, and you got the svg from here <a href=\"https://feathericons.com/?query=globe\">https://feathericons.com/?query=globe</a>?</p>",
        "id": 1308724,
        "sender_full_name": "Yash RE",
        "timestamp": 1641970019
    },
    {
        "content": "<p>I looked at the svg and it doesn't have any elements which should act weirdly like that, but I'll try follow the same steps on my end and see what happens</p>",
        "id": 1308725,
        "sender_full_name": "Yash RE",
        "timestamp": 1641970087
    },
    {
        "content": "<p><span class=\"user-mention silent\" data-user-id=\"9808\">Yash RE</span> <a href=\"#narrow/stream/101-design/topic/globe.20icon.20for.20world-public.20streams/near/1308724\">said</a>:</p>\n<blockquote>\n<p>I see, and you got the svg from here <a href=\"https://feathericons.com/?query=globe\">https://feathericons.com/?query=globe</a>?</p>\n</blockquote>\n<p>Yes, the same globe.svg</p>",
        "id": 1308732,
        "sender_full_name": "Shivam Deotarse",
        "timestamp": 1641970870
    },
    {
        "content": "<p><span class=\"user-mention\" data-user-id=\"22454\">@Shivam Deotarse</span> here is the globe icon which is a shape rather than set of lines</p>",
        "id": 1309136,
        "sender_full_name": "Vlad Korobov",
        "timestamp": 1642022460
    },
    {
        "content": "<p><a href=\"/user_uploads/2/1b/afw2HuyK7WcuJGQmnU1hY2f1/globe-shape.svg\">globe-shape.svg</a></p>",
        "id": 1309137,
        "sender_full_name": "Vlad Korobov",
        "timestamp": 1642022493
    },
    {
        "content": "<p>it should work fine in the list of streams</p>",
        "id": 1309139,
        "sender_full_name": "Vlad Korobov",
        "timestamp": 1642022503
    },
    {
        "content": "<p>I guess, the only thing that you should do is to replace fill property with currectColor, or its done in JS already and you want to remove fill property from the SVG</p>",
        "id": 1309147,
        "sender_full_name": "Vlad Korobov",
        "timestamp": 1642022673
    },
    {
        "content": "<p>quick test inside the browsers tells me that now the icon is correct <a href=\"/user_uploads/2/55/b3vBhj5rFNsrvXe7Q6Nu2j_l/image.png\">image.png</a></p>\n<div class=\"message_inline_image\"><a href=\"/user_uploads/2/55/b3vBhj5rFNsrvXe7Q6Nu2j_l/image.png\" title=\"image.png\"><img src=\"/user_uploads/2/55/b3vBhj5rFNsrvXe7Q6Nu2j_l/image.png\"></a></div>",
        "id": 1309149,
        "sender_full_name": "Vlad Korobov",
        "timestamp": 1642022715
    },
    {
        "content": "<p>Cool.  We'd of course want to polish the details so it looks visually centered properly if we're swapping the icon.  I think I like that better visually than the existing icon; but perhaps we should do a side-by-side comparison of some sort to crystalize our thinking on that?</p>",
        "id": 1309411,
        "sender_full_name": "Tim Abbott",
        "timestamp": 1642030374
    },
    {
        "content": "<p>well I just tested that its working and svg isn't broken. As a metaphor I think is a good one.With a future design update hashtag icon would play better with this globe icon</p>",
        "id": 1309463,
        "sender_full_name": "Vlad Korobov",
        "timestamp": 1642034103
    },
    {
        "content": "<p><span class=\"user-mention silent\" data-user-id=\"22817\">tsker</span> has marked this topic as resolved.</p>",
        "id": 1309532,
        "sender_full_name": "Notification Bot",
        "timestamp": 1642044292
    },
    {
        "content": "<p><span class=\"user-mention silent\" data-user-id=\"22817\">tsker</span> has marked this topic as unresolved.</p>",
        "id": 1309533,
        "sender_full_name": "Notification Bot",
        "timestamp": 1642044296
    },
    {
        "content": "<p><span class=\"user-mention\" data-user-id=\"22454\">@Shivam Deotarse</span> let me take over this issue.</p>",
        "id": 1328905,
        "sender_full_name": "Aman (amanagr)",
        "timestamp": 1644924487
    },
    {
        "content": "<p><a href=\"/user_uploads/2/3c/s1A_9C6dUMc1BSqIPD_PD0Pf/Screenshot-2022-02-15-at-7.12.56-PM.png\">Screenshot-2022-02-15-at-7.12.56-PM.png</a> <a href=\"/user_uploads/2/f0/WEo80e3cbF-aCE2sxUL4OVZT/Screenshot-2022-02-15-at-7.13.10-PM.png\">Screenshot-2022-02-15-at-7.13.10-PM.png</a></p>\n<div class=\"message_inline_image\"><a href=\"/user_uploads/2/3c/s1A_9C6dUMc1BSqIPD_PD0Pf/Screenshot-2022-02-15-at-7.12.56-PM.png\" title=\"Screenshot-2022-02-15-at-7.12.56-PM.png\"><img src=\"/user_uploads/2/3c/s1A_9C6dUMc1BSqIPD_PD0Pf/Screenshot-2022-02-15-at-7.12.56-PM.png\"></a></div><div class=\"message_inline_image\"><a href=\"/user_uploads/2/f0/WEo80e3cbF-aCE2sxUL4OVZT/Screenshot-2022-02-15-at-7.13.10-PM.png\" title=\"Screenshot-2022-02-15-at-7.13.10-PM.png\"><img src=\"/user_uploads/2/f0/WEo80e3cbF-aCE2sxUL4OVZT/Screenshot-2022-02-15-at-7.13.10-PM.png\"></a></div>",
        "id": 1328949,
        "sender_full_name": "Aman (amanagr)",
        "timestamp": 1644932606
    },
    {
        "content": "<p>I like the current icon better. It is easier on my eyes and more intuitive.</p>",
        "id": 1328951,
        "sender_full_name": "Aman (amanagr)",
        "timestamp": 1644932652
    },
    {
        "content": "<p>The question is if it should be easier or not</p>",
        "id": 1328968,
        "sender_full_name": "Vlad Korobov",
        "timestamp": 1644933453
    },
    {
        "content": "<p>I'm not that picky about little things, but other might be... the world on the current icon is North America <span aria-label=\"smile\" class=\"emoji emoji-1f642\" role=\"img\" title=\"smile\">:smile:</span></p>",
        "id": 1328970,
        "sender_full_name": "Vlad Korobov",
        "timestamp": 1644933506
    },
    {
        "content": "<p>Well, I see the icon as NA being a part of the world.</p>",
        "id": 1328976,
        "sender_full_name": "Aman (amanagr)",
        "timestamp": 1644933641
    },
    {
        "content": "<p>I'm ok with any icon... for some reason I thought that public stream should be very distinctive. The current globe icon is easy to lose among the others</p>",
        "id": 1328978,
        "sender_full_name": "Vlad Korobov",
        "timestamp": 1644933690
    },
    {
        "content": "<p>(note that we have some broader discussion on <a class=\"stream-topic\" data-stream-id=\"101\" href=\"/#narrow/stream/101-design/topic/web.20public.20streams\">#design &gt; web public streams</a> )</p>",
        "id": 1328980,
        "sender_full_name": "Steve Howell",
        "timestamp": 1644933741
    },
    {
        "content": "<p><span class=\"user-mention\" data-user-id=\"5140\">@Aman Agrawal (amanagr)</span> the icons in your screenshot are different sizes — is it possible to scale the new one so it's the same size? It's hard to compare, changing the icon and size at the same time.</p>",
        "id": 1328992,
        "sender_full_name": "Wesley Aptekar-Cassels",
        "timestamp": 1644934672
    },
    {
        "content": "<p><a href=\"/user_uploads/2/5c/dl4gQUkESzfKg6BAMNa47spc/Screenshot-2022-02-15-at-7.52.08-PM.png\">Screenshot-2022-02-15-at-7.52.08-PM.png</a></p>\n<div class=\"message_inline_image\"><a href=\"/user_uploads/2/5c/dl4gQUkESzfKg6BAMNa47spc/Screenshot-2022-02-15-at-7.52.08-PM.png\" title=\"Screenshot-2022-02-15-at-7.52.08-PM.png\"><img src=\"/user_uploads/2/5c/dl4gQUkESzfKg6BAMNa47spc/Screenshot-2022-02-15-at-7.52.08-PM.png\"></a></div>",
        "id": 1328993,
        "sender_full_name": "Aman (amanagr)",
        "timestamp": 1644934937
    },
    {
        "content": "<p>These don't feel bad after using the UI with them for a while.</p>",
        "id": 1329147,
        "sender_full_name": "Aman (amanagr)",
        "timestamp": 1644951314
    },
    {
        "content": "<p>Could you share a screenshot for a logged in user? I'd be curious how it looks next to hashes for regular public streams; I'm guessing the newly proposed icon might fit well with them stylistically.</p>",
        "id": 1329455,
        "sender_full_name": "Alya Abbott",
        "timestamp": 1644967739
    },
    {
        "content": "<p>re: North America</p>\n<p>It's probably not a huge deal, but it is a common complaint of folks on the non-north-america part of the world that the \"default\" side of the world is usually not theirs. I remember something about Facebook changing it depending on location</p>",
        "id": 1329551,
        "sender_full_name": "Evy",
        "timestamp": 1644972692
    },
    {
        "content": "<p>Obscure comedy reference to globes:</p>\n<p><a href=\"https://m.youtube.com/watch?v=a9eTru16aDc\">https://m.youtube.com/watch?v=a9eTru16aDc</a></p>\n<div class=\"youtube-video message_inline_image\"><a data-id=\"a9eTru16aDc\" href=\"https://m.youtube.com/watch?v=a9eTru16aDc\"><img src=\"/external_content/c7988ed15f45af07ac55a6dec301640c1fd389b0/68747470733a2f2f692e7974696d672e636f6d2f76692f61396554727531366144632f64656661756c742e6a7067\"></a></div>",
        "id": 1329555,
        "sender_full_name": "Steve Howell",
        "timestamp": 1644972918
    },
    {
        "content": "<p><span class=\"user-mention silent\" data-user-id=\"19257\">Alya Abbott</span> <a href=\"#narrow/stream/101-design/topic/globe.20icon.20for.20world-public.20streams/near/1329455\">said</a>:</p>\n<blockquote>\n<p>Could you share a screenshot for a logged in user? I'd be curious how it looks next to hashes for regular public streams; I'm guessing the newly proposed icon might fit well with them stylistically.</p>\n</blockquote>\n<p><a href=\"/user_uploads/2/0/sXwfCwBbHtfHiWpwJheaF71a/image.png\">image.png</a></p>\n<div class=\"message_inline_image\"><a href=\"/user_uploads/2/0/sXwfCwBbHtfHiWpwJheaF71a/image.png\" title=\"image.png\"><img src=\"/user_uploads/2/0/sXwfCwBbHtfHiWpwJheaF71a/image.png\"></a></div>",
        "id": 1329729,
        "sender_full_name": "Aman (amanagr)",
        "timestamp": 1644987262
    },
    {
        "content": "<p>I see an alignment problem: the column of hashes and globes is centered in the left sidebar, but left-aligned in the recent topics list.</p>",
        "id": 1329731,
        "sender_full_name": "Anders Kaseorg",
        "timestamp": 1644987333
    },
    {
        "content": "<p>The vertical alignment looks a little off too, unless I'm imagining it?</p>",
        "id": 1330542,
        "sender_full_name": "Alya Abbott",
        "timestamp": 1645060187
    },
    {
        "content": "<p>But I like the new globe.</p>",
        "id": 1330543,
        "sender_full_name": "Alya Abbott",
        "timestamp": 1645060195
    },
    {
        "content": "<p>You￼￼ are correct about alignment guys</p>",
        "id": 1330549,
        "sender_full_name": "Vlad Korobov",
        "timestamp": 1645061427
    },
    {
        "content": "<p>The mobile app displays the same globe icon that the web app does now, if this changes we'll want to be able to use it in the app as well.</p>",
        "id": 1336298,
        "sender_full_name": "Austin Riba",
        "timestamp": 1646081224
    },
    {
        "content": "<p>Let's get a version of this we can test-deploy, so we can validate this change.</p>",
        "id": 1336346,
        "sender_full_name": "Tim Abbott",
        "timestamp": 1646082642
    },
    {
        "content": "<p>The updated globe icon has been merged and is running here.</p>",
        "id": 1337407,
        "sender_full_name": "Tim Abbott",
        "timestamp": 1646176389
    },
    {
        "content": "<p>There's one outstanding bug here that I'm aware of, which is not new with the updated icon, which is that \"Recent topics\" doesn't align things how we will want it to.</p>",
        "id": 1337409,
        "sender_full_name": "Tim Abbott",
        "timestamp": 1646176428
    },
    {
        "content": "<p>I like how it looks in the left sidebar!</p>",
        "id": 1337480,
        "sender_full_name": "Alya Abbott",
        "timestamp": 1646178559
    },
    {
        "content": "<p>The icon is misaligned and not colored in the navbar.</p>\n<div class=\"message_inline_image\"><a href=\"/user_uploads/2/69/2uK5Zc1o7qQ2hT5RdAeA9ktV/image.png\"><img src=\"/user_uploads/2/69/2uK5Zc1o7qQ2hT5RdAeA9ktV/image.png\"></a></div>",
        "id": 1337642,
        "sender_full_name": "Yash RE",
        "timestamp": 1646200319
    },
    {
        "content": "<p>Hmm, maybe its not \"misaligned\" since its very close to the alignment in the FRB but the alignment does not look good.</p>",
        "id": 1337643,
        "sender_full_name": "Yash RE",
        "timestamp": 1646200454
    },
    {
        "content": "<p>Hm, I think we have a general issue that applies to the private stream icon as well, which is that the vertical alignment seems to be different in the left sidebar vs. the navbar vs. the message header bar.</p>",
        "id": 1337692,
        "sender_full_name": "Alya Abbott",
        "timestamp": 1646208390
    },
    {
        "content": "<p>This change hasn't been announced in <a class=\"stream\" data-stream-id=\"415\" href=\"/#narrow/stream/415-chat.2Ezulip.2Eorg\">#chat.zulip.org</a> .</p>",
        "id": 1337710,
        "sender_full_name": "Rein Zustand",
        "timestamp": 1646218178
    },
    {
        "content": "<p>I think the original icon conveys the fact that it is web public better, because it is unmistakenly a globe.</p>",
        "id": 1337711,
        "sender_full_name": "Rein Zustand",
        "timestamp": 1646218215
    },
    {
        "content": "<p>I'll revisit the icon in the new design.</p>",
        "id": 1337736,
        "sender_full_name": "Vlad Korobov",
        "timestamp": 1646229332
    },
    {
        "content": "<p>The new icon is cleaner to me, but yeah, the old icon conveyed globe better.</p>",
        "id": 1337737,
        "sender_full_name": "Aman (amanagr)",
        "timestamp": 1646229994
    },
    {
        "content": "<p>I also like the new icon, but I think there is always room for improvement.</p>",
        "id": 1337738,
        "sender_full_name": "Steve Howell",
        "timestamp": 1646230497
    },
    {
        "content": "<p><span class=\"user-mention silent\" data-user-id=\"9808\">Yash RE</span> <a href=\"#narrow/stream/101-design/topic/globe.20icon.20for.20world-public.20streams/near/1337643\">said</a>:</p>\n<blockquote>\n<p>Hmm, maybe its not \"misaligned\" since its very close to the alignment in the FRB but the alignment does not look good.</p>\n</blockquote>\n<p>Opened <a href=\"https://github.com/zulip/zulip/pull/21295\">#21295</a>.</p>",
        "id": 1337742,
        "sender_full_name": "Aman (amanagr)",
        "timestamp": 1646230979
    },
    {
        "content": "<p>You know what guys</p>",
        "id": 1337827,
        "sender_full_name": "Vlad Korobov",
        "timestamp": 1646245214
    },
    {
        "content": "<p>The icon is currently used isn’t the one I thought we would</p>",
        "id": 1337828,
        "sender_full_name": "Vlad Korobov",
        "timestamp": 1646245232
    },
    {
        "content": "<p><a href=\"/user_uploads/2/78/HWz0FlvKI-RVoiWoBrlgaBqh/4E568C04-070E-4574-8517-B5E609A187DC.png\">4E568C04-070E-4574-8517-B5E609A187DC.png</a></p>\n<div class=\"message_inline_image\"><a href=\"/user_uploads/2/78/HWz0FlvKI-RVoiWoBrlgaBqh/4E568C04-070E-4574-8517-B5E609A187DC.png\" title=\"4E568C04-070E-4574-8517-B5E609A187DC.png\"><img src=\"/user_uploads/2/78/HWz0FlvKI-RVoiWoBrlgaBqh/4E568C04-070E-4574-8517-B5E609A187DC.png\"></a></div>",
        "id": 1337829,
        "sender_full_name": "Vlad Korobov",
        "timestamp": 1646245240
    },
    {
        "content": "<p>Aman, you shared a screen earlier with a proper icon. The one I see in Zulip web - is a wrong one</p>",
        "id": 1337831,
        "sender_full_name": "Vlad Korobov",
        "timestamp": 1646245347
    },
    {
        "content": "<p><span class=\"user-mention silent\" data-user-id=\"2328\">Rein Zustand</span> <a href=\"#narrow/stream/101-design/topic/globe.20icon.20for.20world-public.20streams/near/1337710\">said</a>:</p>\n<blockquote>\n<p>This change hasn't been announced in <a class=\"stream\" data-stream-id=\"415\" href=\"/#narrow/stream/415-chat.2Ezulip.2Eorg\">#chat.zulip.org</a> .</p>\n</blockquote>\n<p>I believe our current plan is to announce experiments, and not all features that are merged to <code>main</code> and will be rolled out to Zulip Cloud soon (like this one). We may announce some features like this if we specifically need feedback on them, but I don't think we want to create overhead for <span class=\"user-mention silent\" data-user-id=\"7\">Tim Abbott</span> any time a feature is merged.</p>",
        "id": 1337832,
        "sender_full_name": "Alya Abbott",
        "timestamp": 1646245391
    },
    {
        "content": "<p>Yash you screenshot is showing a wrong icon</p>",
        "id": 1337833,
        "sender_full_name": "Vlad Korobov",
        "timestamp": 1646245394
    },
    {
        "content": "<p>Hmm... <span class=\"user-mention\" data-user-id=\"5140\">@Aman Agrawal (amanagr)</span> FYI</p>",
        "id": 1337834,
        "sender_full_name": "Alya Abbott",
        "timestamp": 1646245452
    },
    {
        "content": "<p>Just putting this out there, if we could use the one from FeatherIcons that Vlad posted a screenshot of, it would make things a bit easier on the technical side :)</p>",
        "id": 1337849,
        "sender_full_name": "Austin Riba",
        "timestamp": 1646246669
    },
    {
        "content": "<p><span class=\"user-mention silent\" data-user-id=\"22752\">Austin Riba</span> <a href=\"#narrow/stream/101-design/topic/globe.20icon.20for.20world-public.20streams/near/1337849\">said</a>:</p>\n<blockquote>\n<p>Just putting this out there, if we could use the one from FeatherIcons that Vlad posted a screenshot of, it would make things a bit easier on the technical side <span aria-label=\"smile\" class=\"emoji emoji-1f642\" role=\"img\" title=\"smile\">:smile:</span></p>\n</blockquote>\n<p>I responded in <a class=\"stream-topic\" data-stream-id=\"243\" href=\"/#narrow/stream/243-mobile-team/topic/custom.20icons\">#mobile-team &gt; custom icons</a> on this front, but I think those technical issues are very solvable and we will likely want to solve for other reasons, so I think it'd be better to focus on what icon we think is best.</p>",
        "id": 1338138,
        "sender_full_name": "Tim Abbott",
        "timestamp": 1646267317
    },
    {
        "content": "<p>That said, I tend to agree that the Font Awesome globe is much more obviously a globe to me.  It's possible that consideration is more important than the potential inclusivity benefits of not displaying a specific set of continents; I think we'll probably have a better sense of that when we begin public beta usage next week.</p>",
        "id": 1338142,
        "sender_full_name": "Tim Abbott",
        "timestamp": 1646267431
    },
    {
        "content": "<p><span class=\"user-mention silent\" data-user-id=\"22433\">Vlad Korobov</span> <a href=\"#narrow/stream/101-design/topic/globe.20icon.20for.20world-public.20streams/near/1337828\">said</a>:</p>\n<blockquote>\n<p>The icon is currently used isn’t the one I thought we would</p>\n</blockquote>\n<p>Oops, I must have used the wrong svg. I was experimenting with different ones.</p>",
        "id": 1338260,
        "sender_full_name": "Aman (amanagr)",
        "timestamp": 1646285259
    },
    {
        "content": "<p><a href=\"/user_uploads/2/34/x4dh8tvoMrC0qg1eqoJAwnkp/image.png\">image.png</a> <br>\n<a href=\"/user_uploads/2/96/rRtsLHjzYLldap6Piy5ZdLEi/image.png\">image.png</a> </p>\n<div class=\"message_inline_image\"><a href=\"/user_uploads/2/34/x4dh8tvoMrC0qg1eqoJAwnkp/image.png\" title=\"image.png\"><img src=\"/user_uploads/2/34/x4dh8tvoMrC0qg1eqoJAwnkp/image.png\"></a></div><div class=\"message_inline_image\"><a href=\"/user_uploads/2/96/rRtsLHjzYLldap6Piy5ZdLEi/image.png\" title=\"image.png\"><img src=\"/user_uploads/2/96/rRtsLHjzYLldap6Piy5ZdLEi/image.png\"></a></div><p>How does it look now? I pushed the icon 0.5px below the adjacent text so that it doesn't look misaligned.</p>",
        "id": 1338266,
        "sender_full_name": "Aman (amanagr)",
        "timestamp": 1646287323
    },
    {
        "content": "<p><span class=\"user-mention silent\" data-user-id=\"22433\">Vlad Korobov</span> <a href=\"#narrow/stream/101-design/topic/globe.20icon.20for.20world-public.20streams/near/1309147\">said</a>:</p>\n<blockquote>\n<p>I guess, the only thing that you should do is to replace fill property with currectColor, or its done in JS already and you want to remove fill property from the SVG</p>\n</blockquote>\n<p>You identified the issue correctly here but the solution doesn't work in our case when the svg is rendered as a font. So, I had to convert the icon to png and back to svg so that it renders differently. (As coordinates instead of a shape)</p>",
        "id": 1338267,
        "sender_full_name": "Aman (amanagr)",
        "timestamp": 1646287454
    },
    {
        "content": "<p>What</p>",
        "id": 1338270,
        "sender_full_name": "Anders Kaseorg",
        "timestamp": 1646287873
    },
    {
        "content": "<p>I guess that’s why it’s slightly asymmetric and 4× longer than it needs to be. (The function you were looking for is Inkscape’s <strong>Stroke to Path</strong>.)</p>\n<div class=\"spoiler-block\"><div class=\"spoiler-header\">\n</div><div class=\"spoiler-content\" aria-hidden=\"true\">\n<div class=\"codehilite\" data-code-language=\"Diff\"><pre><span></span><code><span class=\"gd\">-&lt;?xml version=\"1.0\" standalone=\"no\"?&gt;</span><span class=\"w\"></span>\n<span class=\"gd\">-&lt;!DOCTYPE svg PUBLIC \"-//W3C//DTD SVG 20010904//EN\"</span><span class=\"w\"></span>\n<span class=\"gd\">- \"http://www.w3.org/TR/2001/REC-SVG-20010904/DTD/svg10.dtd\"&gt;</span><span class=\"w\"></span>\n<span class=\"gd\">-&lt;svg version=\"1.0\" xmlns=\"http://www.w3.org/2000/svg\"</span><span class=\"w\"></span>\n<span class=\"gd\">- width=\"512.000000pt\" height=\"512.000000pt\" viewBox=\"0 0 512.000000 512.000000\"</span><span class=\"w\"></span>\n<span class=\"gd\">- preserveAspectRatio=\"xMidYMid meet\"&gt;</span><span class=\"w\"></span>\n<span class=\"gd\">-</span><span class=\"w\"></span>\n<span class=\"gd\">-&lt;g transform=\"translate(0.000000,512.000000) scale(0.100000,-0.100000)\"</span><span class=\"w\"></span>\n<span class=\"gd\">-fill=\"#000000\" stroke=\"none\"&gt;</span><span class=\"w\"></span>\n<span class=\"gd\">-&lt;path d=\"M2380 5114 c-19 -2 -78 -9 -130 -14 -330 -36 -695 -160 -990 -336</span><span class=\"w\"></span>\n<span class=\"gd\">--375 -224 -680 -529 -904 -904 -175 -292 -291 -632 -338 -990 -16 -123 -16</span><span class=\"w\"></span>\n<span class=\"gd\">--497 0 -620 82 -623 356 -1150 820 -1581 256 -239 575 -425 922 -539 274 -91</span><span class=\"w\"></span>\n<span class=\"gd\">-491 -124 800 -124 228 0 329 9 530 50 689 141 1304 583 1674 1204 175 292 291</span><span class=\"w\"></span>\n<span class=\"gd\">-632 338 990 16 123 16 497 0 620 -47 358 -163 698 -338 990 -224 375 -529 680</span><span class=\"w\"></span>\n<span class=\"gd\">--904 904 -289 173 -634 291 -980 336 -88 12 -438 21 -500 14z m281 -320 c109</span><span class=\"w\"></span>\n<span class=\"gd\">--55 219 -193 320 -399 81 -167 125 -292 184 -517 l43 -168 -648 0 -648 0 43</span><span class=\"w\"></span>\n<span class=\"gd\">-168 c59 225 103 350 184 517 114 233 237 376 360 416 38 12 123 3 162 -17z</span><span class=\"w\"></span>\n<span class=\"gd\">-m-695 -86 c-143 -232 -277 -596 -346 -940 l-11 -58 -495 0 c-272 0 -494 3</span><span class=\"w\"></span>\n<span class=\"gd\">--494 6 0 12 95 152 159 234 271 349 667 627 1086 760 55 17 105 33 110 35 6 2</span><span class=\"w\"></span>\n<span class=\"gd\">-12 4 14 4 1 1 -9 -18 -23 -41z m1254 14 c428 -128 845 -415 1121 -772 64 -82</span><span class=\"w\"></span>\n<span class=\"gd\">-159 -222 159 -234 0 -3 -222 -6 -494 -6 l-495 0 -11 58 c-69 344 -203 708</span><span class=\"w\"></span>\n<span class=\"gd\">--346 940 -16 25 -21 40 -13 38 8 -3 43 -14 79 -24z m-1664 -1334 c-7 -31 -23</span><span class=\"w\"></span>\n<span class=\"gd\">--174 -38 -338 -7 -79 -12 -283 -12 -495 0 -342 5 -428 40 -762 l7 -63 -550 0</span><span class=\"w\"></span>\n<span class=\"gd\">--550 0 -36 113 c-73 224 -104 401 -114 637 -11 296 33 570 142 883 l17 47 549</span><span class=\"w\"></span>\n<span class=\"gd\">-0 549 0 -4 -22z m1704 15 c0 -5 5 -37 10 -73 59 -391 63 -993 11 -1450 l-16</span><span class=\"w\"></span>\n<span class=\"gd\">--145 -705 0 -705 0 -16 145 c-52 457 -48 1059 11 1450 5 36 10 68 10 73 0 4</span><span class=\"w\"></span>\n<span class=\"gd\">-315 7 700 7 385 0 700 -3 700 -7z m1415 -40 c183 -524 192 -1014 28 -1520</span><span class=\"w\"></span>\n<span class=\"gd\">-l-36 -113 -550 0 -550 0 7 63 c35 334 40 420 40 762 0 212 -5 416 -12 495 -15</span><span class=\"w\"></span>\n<span class=\"gd\">-164 -31 307 -38 338 l-4 22 549 0 549 0 17 -47z m-3043 -2063 c77 -344 198</span><span class=\"w\"></span>\n<span class=\"gd\">--667 334 -888 16 -25 21 -40 13 -38 -8 3 -43 14 -79 24 -411 123 -813 393</span><span class=\"w\"></span>\n<span class=\"gd\">--1085 727 -74 91 -205 280 -205 296 0 5 216 8 497 7 l497 -3 28 -125z m1578</span><span class=\"w\"></span>\n<span class=\"gd\">-123 c0 -24 -94 -364 -125 -453 -84 -243 -230 -494 -341 -586 -76 -64 -110 -78</span><span class=\"w\"></span>\n<span class=\"gd\">--184 -78 -74 0 -108 14 -184 78 -111 92 -257 343 -341 586 -31 89 -125 429</span><span class=\"w\"></span>\n<span class=\"gd\">--125 453 0 4 293 7 650 7 358 0 650 -3 650 -7z m1300 -2 c0 -4 -30 -53 -66</span><span class=\"w\"></span>\n<span class=\"gd\">--107 -302 -453 -738 -773 -1262 -928 l-54 -15 26 42 c134 217 258 545 330 872</span><span class=\"w\"></span>\n<span class=\"gd\">-15 66 29 126 31 133 3 9 112 12 500 12 274 0 495 -4 495 -9z\"/&gt;</span><span class=\"w\"></span>\n<span class=\"gd\">-&lt;/g&gt;</span><span class=\"w\"></span>\n<span class=\"gi\">+&lt;svg viewBox=\"0 0 512 512\" xmlns=\"http://www.w3.org/2000/svg\"&gt;</span><span class=\"w\"></span>\n<span class=\"gi\">+&lt;path d=\"M256 0a256 256 0 1 0 0 512 256 256 0 0 0 0-512Zm0 30a226 226 0 1</span><span class=\"w\"></span>\n<span class=\"gi\">+1 0 452 226 226 0 0 1 0-452Zm0-30c-18 0-34 10-47 24-12 14-23 33-31 56-18</span><span class=\"w\"></span>\n<span class=\"gi\">+46-28 108-28 176s10 130 28 176c8 23 19 42 31 56 13 14 29 24 47 24s34-10</span><span class=\"w\"></span>\n<span class=\"gi\">+47-24c12-14 23-33 31-56 18-46 28-108</span><span class=\"w\"></span>\n<span class=\"gi\">+28-176s-10-130-28-176c-8-23-19-42-31-56a64 64 0 0 0-47-24Zm0 30c7 0 15 4</span><span class=\"w\"></span>\n<span class=\"gi\">+24 14s19 26 26 47c16 41 26 100 26 165s-10 124-26 165c-7 21-17 37-26 47s-17</span><span class=\"w\"></span>\n<span class=\"gi\">+14-24 14-15-4-24-14-19-26-26-47c-16-41-26-100-26-165s10-124 26-165c7-21</span><span class=\"w\"></span>\n<span class=\"gi\">+17-37 26-47s17-14 24-14ZM36 142v30h440v-30zm0 198v30h440v-30z\"/&gt;</span><span class=\"w\"></span>\n<span class=\"w\"> </span>&lt;/svg&gt;<span class=\"w\"></span>\n</code></pre></div>\n</div></div>",
        "id": 1338297,
        "sender_full_name": "Anders Kaseorg",
        "timestamp": 1646291768
    },
    {
        "content": "<p>Thanks, that works well. I am not sure if it looks better, though.</p>\n<p><a href=\"/user_uploads/2/8f/sqmIgc_ytvMboRxdJvDmhf9o/image.png\">stroke to path</a></p>\n<div class=\"message_inline_image\"><a href=\"/user_uploads/2/8f/sqmIgc_ytvMboRxdJvDmhf9o/image.png\" title=\"stroke to path\"><img src=\"/user_uploads/2/8f/sqmIgc_ytvMboRxdJvDmhf9o/image.png\"></a></div>",
        "id": 1340452,
        "sender_full_name": "Aman (amanagr)",
        "timestamp": 1646715601
    },
    {
        "content": "<p><a href=\"/user_uploads/2/9e/4QkTCDteLlV9Vp8F_q0l_tNN/image.png\">svg to png to svg</a></p>\n<div class=\"message_inline_image\"><a href=\"/user_uploads/2/9e/4QkTCDteLlV9Vp8F_q0l_tNN/image.png\" title=\"svg to png to svg\"><img src=\"/user_uploads/2/9e/4QkTCDteLlV9Vp8F_q0l_tNN/image.png\"></a></div>",
        "id": 1340453,
        "sender_full_name": "Aman (amanagr)",
        "timestamp": 1646715634
    },
    {
        "content": "<p>One downside of this icon is that it will not make any sense on high resolution screens.<br>\n<a href=\"/user_uploads/2/44/YbKjxMwdUwFvLT9_5l5B_h50/image.png\">4k screen 100%</a></p>\n<div class=\"message_inline_image\"><a href=\"/user_uploads/2/44/YbKjxMwdUwFvLT9_5l5B_h50/image.png\" title=\"4k screen 100%\"><img src=\"/user_uploads/2/44/YbKjxMwdUwFvLT9_5l5B_h50/image.png\"></a></div>",
        "id": 1340454,
        "sender_full_name": "Aman (amanagr)",
        "timestamp": 1646715792
    },
    {
        "content": "<p>I am waiting on some feedback from others here.</p>",
        "id": 1345821,
        "sender_full_name": "Aman (amanagr)",
        "timestamp": 1647395048
    },
    {
        "content": "<p><span class=\"user-mention\" data-user-id=\"5140\">@Aman Agrawal (amanagr)</span> can we try that one <a href=\"/user_uploads/2/5e/K93VZUvzHIf4SOR6THk9tY9D/icon-earth.svg\">icon-earth.svg</a> ?</p>",
        "id": 1345824,
        "sender_full_name": "Vlad Korobov",
        "timestamp": 1647395933
    },
    {
        "content": "<p>Please remember to preserve licensing and attribution information when proposing icons. And if this is an icon available in an NPM package, we should import it that way rather than copying the file.</p>",
        "id": 1345832,
        "sender_full_name": "Anders Kaseorg",
        "timestamp": 1647397657
    },
    {
        "content": "<p><code>icon-earth.svg</code> seems to have the focus on North America problem we were trying to steer clear of, though perhaps there's more ocean than in the original one?</p>\n<p>The <code>stroke to path</code> screenshot above looks fine to me. I like that style of globe next to the hashes.</p>",
        "id": 1345841,
        "sender_full_name": "Alya Abbott",
        "timestamp": 1647403564
    },
    {
        "content": "<p>For the high res screenshot, I think you'd have to zoom in for the text to be readable in any case.</p>",
        "id": 1345842,
        "sender_full_name": "Alya Abbott",
        "timestamp": 1647403591
    },
    {
        "content": "<p><span class=\"user-mention silent\" data-user-id=\"699\">Anders Kaseorg</span> <a href=\"#narrow/stream/101-design/topic/globe.20icon.20for.20world-public.20streams/near/1345832\">said</a>:</p>\n<blockquote>\n<p>Please remember to preserve licensing and attribution information when proposing icons. And if this is an icon available in an NPM package, we should import it that way rather than copying the file.</p>\n</blockquote>\n<p>I do remember about it. I'm using either Feather icons or my commercial license to <a href=\"http://icons8.com\">icons8.com</a> or drawing icons myself.</p>",
        "id": 1345862,
        "sender_full_name": "Vlad Korobov",
        "timestamp": 1647406181
    },
    {
        "content": "<p><span class=\"user-mention silent\" data-user-id=\"19257\">Alya Abbott</span> <a href=\"#narrow/stream/101-design/topic/globe.20icon.20for.20world-public.20streams/near/1345841\">said</a>:</p>\n<blockquote>\n<p><code>icon-earth.svg</code> seems to have the focus on North America problem we were trying to steer clear of, though perhaps there's more ocean than in the original one?</p>\n<p>The <code>stroke to path</code> screenshot above looks fine to me. I like that style of globe next to the hashes.</p>\n</blockquote>\n<p>Icon is a symbol, I didn't know that there was some goal to don't show something. I don't think we should optimize for that. The goal should be a better metaphor recognition. But if you prefer the initial globe that I suggested instead of this one I'm ok with that.</p>",
        "id": 1345867,
        "sender_full_name": "Vlad Korobov",
        "timestamp": 1647406287
    },
    {
        "content": "<p>We generally can't use icons from a paid source -- it seems very likely such icons would have a license that restricts redistribution that would not be compatible with our open source license for Zulip overall.</p>",
        "id": 1345903,
        "sender_full_name": "Tim Abbott",
        "timestamp": 1647408205
    },
    {
        "content": "<p>(I haven't looked up the licensing rules for <a href=\"http://icons8.com\">icons8.com</a>)</p>",
        "id": 1345904,
        "sender_full_name": "Tim Abbott",
        "timestamp": 1647408243
    },
    {
        "content": "<p>Do I need to get some kind of license confirmation?</p>",
        "id": 1345905,
        "sender_full_name": "Vlad Korobov",
        "timestamp": 1647408284
    },
    {
        "content": "<p>About the icon itself, would something like this be better? <a href=\"/user_uploads/2/f9/umr_K74jhbKWnVG7Rl0P5ac1/image.png\">image.png</a></p>\n<div class=\"message_inline_image\"><a href=\"/user_uploads/2/f9/umr_K74jhbKWnVG7Rl0P5ac1/image.png\" title=\"image.png\"><img src=\"/user_uploads/2/f9/umr_K74jhbKWnVG7Rl0P5ac1/image.png\"></a></div>",
        "id": 1345907,
        "sender_full_name": "Vlad Korobov",
        "timestamp": 1647408307
    },
    {
        "content": "<p><a href=\"https://www.svgrepo.com/vectors/globe/\">https://www.svgrepo.com/vectors/globe/</a> has some interesting open source licensed icons.</p>",
        "id": 1345947,
        "sender_full_name": "Aman (amanagr)",
        "timestamp": 1647409725
    },
    {
        "content": "<p><a href=\"/user_uploads/2/70/DHyHN8Zd-QV8wjT4A1f-4gLL/Screenshot-2022-03-16-at-11.24.50-AM.png\">Screenshot-2022-03-16-at-11.24.50-AM.png</a> <a href=\"/user_uploads/2/53/zKPBEAxKz4NCthlPVrZ14PmV/Screenshot-2022-03-16-at-11.27.57-AM.png\">Screenshot-2022-03-16-at-11.27.57-AM.png</a> <a href=\"/user_uploads/2/4/igpKeXNefdkcVdx-nrbnbEd2/Screenshot-2022-03-16-at-11.28.47-AM.png\">Screenshot-2022-03-16-at-11.28.47-AM.png</a></p>\n<div class=\"message_inline_image\"><a href=\"/user_uploads/2/70/DHyHN8Zd-QV8wjT4A1f-4gLL/Screenshot-2022-03-16-at-11.24.50-AM.png\" title=\"Screenshot-2022-03-16-at-11.24.50-AM.png\"><img src=\"/user_uploads/2/70/DHyHN8Zd-QV8wjT4A1f-4gLL/Screenshot-2022-03-16-at-11.24.50-AM.png\"></a></div><div class=\"message_inline_image\"><a href=\"/user_uploads/2/53/zKPBEAxKz4NCthlPVrZ14PmV/Screenshot-2022-03-16-at-11.27.57-AM.png\" title=\"Screenshot-2022-03-16-at-11.27.57-AM.png\"><img src=\"/user_uploads/2/53/zKPBEAxKz4NCthlPVrZ14PmV/Screenshot-2022-03-16-at-11.27.57-AM.png\"></a></div><div class=\"message_inline_image\"><a href=\"/user_uploads/2/4/igpKeXNefdkcVdx-nrbnbEd2/Screenshot-2022-03-16-at-11.28.47-AM.png\" title=\"Screenshot-2022-03-16-at-11.28.47-AM.png\"><img src=\"/user_uploads/2/4/igpKeXNefdkcVdx-nrbnbEd2/Screenshot-2022-03-16-at-11.28.47-AM.png\"></a></div>",
        "id": 1345950,
        "sender_full_name": "Aman (amanagr)",
        "timestamp": 1647410347
    },
    {
        "content": "<p><a href=\"/user_uploads/2/6b/013R7qrRA5QnlUOY6L7YPZi5/Screenshot-2022-03-16-at-11.30.49-AM.png\">Screenshot-2022-03-16-at-11.30.49-AM.png</a></p>\n<div class=\"message_inline_image\"><a href=\"/user_uploads/2/6b/013R7qrRA5QnlUOY6L7YPZi5/Screenshot-2022-03-16-at-11.30.49-AM.png\" title=\"Screenshot-2022-03-16-at-11.30.49-AM.png\"><img src=\"/user_uploads/2/6b/013R7qrRA5QnlUOY6L7YPZi5/Screenshot-2022-03-16-at-11.30.49-AM.png\"></a></div>",
        "id": 1345953,
        "sender_full_name": "Aman (amanagr)",
        "timestamp": 1647410458
    },
    {
        "content": "<p><a href=\"/user_uploads/2/13/xmd6UgBR70B77RW3YVExYX-b/Screenshot-2022-03-16-at-11.35.07-AM.png\">Screenshot-2022-03-16-at-11.35.07-AM.png</a></p>\n<div class=\"message_inline_image\"><a href=\"/user_uploads/2/13/xmd6UgBR70B77RW3YVExYX-b/Screenshot-2022-03-16-at-11.35.07-AM.png\" title=\"Screenshot-2022-03-16-at-11.35.07-AM.png\"><img src=\"/user_uploads/2/13/xmd6UgBR70B77RW3YVExYX-b/Screenshot-2022-03-16-at-11.35.07-AM.png\"></a></div>",
        "id": 1345960,
        "sender_full_name": "Aman (amanagr)",
        "timestamp": 1647410715
    },
    {
        "content": "<p>(ignore the alignment for now)</p>",
        "id": 1345963,
        "sender_full_name": "Aman (amanagr)",
        "timestamp": 1647410760
    },
    {
        "content": "<p>The Icons8 license has several clauses that are clearly incompatible with inclusion in an open-source project.</p>\n<blockquote>\n<p>The Licensee may not:</p>\n<ul>\n<li>Sublicense, distribute, sell, assign, convey, or otherwise transfer this license nor any of the Licensee's rights, duties, or legal responsibilities under this Agreement;</li>\n<li>Sell, resell, license, or distribute its' final product in a manner allowing others or third parties to extract or access Licensed Material as stand-alone files;<br>\n…</li>\n<li>Distribute, export, post, upload, or download Licensed Material online in a the downloadable format or enable Licensed Material to be accessed; downloaded, or distributed in any manner that would be prohibited by this Agreement;</li>\n</ul>\n</blockquote>\n<p>which is pretty typical for commercial asset licensing.</p>",
        "id": 1345977,
        "sender_full_name": "Anders Kaseorg",
        "timestamp": 1647411343
    },
    {
        "content": "<p>Just so I understand, do folks have some concern about using the icon Vlad suggested earlier?</p>\n<p><span class=\"user-mention silent\" data-user-id=\"22433\">Vlad Korobov</span> <a href=\"#narrow/stream/101-design/topic/globe.20icon.20for.20world-public.20streams/near/1306614\">said</a>:</p>\n<blockquote>\n<p>How about <a href=\"/user_uploads/2/91/Op200bT3gykgMdFq9iW5CvdM/image.png\">image.png</a></p>\n</blockquote>",
        "id": 1345980,
        "sender_full_name": "Alya Abbott",
        "timestamp": 1647411526
    },
    {
        "content": "<p>Feather-icons is a fine source (MIT license).</p>",
        "id": 1345982,
        "sender_full_name": "Anders Kaseorg",
        "timestamp": 1647412327
    },
    {
        "content": "<p><a href=\"https://github.com/google/material-design-icons\">Material design icons</a> (Apache 2.0 license) has an <a href=\"https://fonts.google.com/icons?selected=Material+Icons:public:\">identical icon</a> to Vlad’s icon-earth.svg. (It looks like the Icons8 team may have been involved in developing that set. We can safely assume Google is careful enough to get the licensing details right.)</p>",
        "id": 1345983,
        "sender_full_name": "Anders Kaseorg",
        "timestamp": 1647412602
    },
    {
        "content": "<p>Yeh, I actually use Material icons on icons8 which are redrawn Material icons by Icons8. So it wouldn't be problem for me to find replacement to Icons8</p>",
        "id": 1345990,
        "sender_full_name": "Vlad Korobov",
        "timestamp": 1647413408
    },
    {
        "content": "<p>From a visual standpoint, my favorite of the icon proposals is the Font Awesome one we had originally. A lot of these other options don't parse as a globe to me at the size we'll be using them at all -- they parse as a disk with a scribble inside. And I think \"Is this immediately recognized as a globe\" is a pretty important consideration for what we're using this icon for.</p>\n<p>Second best on that standpoint are the globes with longitude/latitude lines, like what we currently have.</p>",
        "id": 1346225,
        "sender_full_name": "Tim Abbott",
        "timestamp": 1647452327
    },
    {
        "content": "<p>Which icon was that -- was it the one centered on North America?</p>\n<p><a href=\"#narrow/stream/101-design/topic/globe.20icon.20for.20world-public.20streams/near/1306189\">Earlier in the thread</a>, I felt that the Material Design version of that icon: <a href=\"/user_uploads/2/40/DwwMz2Sjb3FmnyqkrRK0X_JY/image.png\">image.png</a> <br>\n<a href=\"https://fonts.google.com/icons?selected=Material+Icons&amp;icon.query=globe\">https://fonts.google.com/icons?selected=Material+Icons&amp;icon.query=globe</a></p>\n<div class=\"message_inline_image\"><a href=\"/user_uploads/2/40/DwwMz2Sjb3FmnyqkrRK0X_JY/image.png\" title=\"image.png\"><img src=\"/user_uploads/2/40/DwwMz2Sjb3FmnyqkrRK0X_JY/image.png\"></a></div><p>was somewhat more legible than that one, while based on the same concept. Also not quite so blatantly centered right on North America, which feels like an improvement.</p>",
        "id": 1346607,
        "sender_full_name": "Greg Price",
        "timestamp": 1647475465
    },
    {
        "content": "<p>FWIW on my screen the current globe looks… choppier, more pixelated, somehow than the other stream icons. <a href=\"/user_uploads/2/b6/KkI9VMTjteHKYcxj68sgyKDJ/image.png\">image.png</a></p>\n<div class=\"message_inline_image\"><a href=\"/user_uploads/2/b6/KkI9VMTjteHKYcxj68sgyKDJ/image.png\" title=\"image.png\"><img src=\"/user_uploads/2/b6/KkI9VMTjteHKYcxj68sgyKDJ/image.png\"></a></div>",
        "id": 1346609,
        "sender_full_name": "Greg Price",
        "timestamp": 1647475822
    },
    {
        "content": "<p><span class=\"user-mention\" data-user-id=\"7\">@Tim Abbott</span> I'm a bit confused by your comment. Could you help me to understand it?</p>\n<blockquote>\n<p>my favorite of the icon proposals is the Font Awesome one we had originally</p>\n</blockquote>\n<p>Which one is that exactly?<br>\nFA 4 globe: <a href=\"/user_uploads/2/1b/J71hFI1gUOHEBTSr0sARcIU0/image.png\">image.png</a> </p>\n<div class=\"message_inline_image\"><a href=\"/user_uploads/2/1b/J71hFI1gUOHEBTSr0sARcIU0/image.png\" title=\"image.png\"><img src=\"/user_uploads/2/1b/J71hFI1gUOHEBTSr0sARcIU0/image.png\"></a></div><p>FA 6 globes <a href=\"/user_uploads/2/65/HjqKFHPE6h7_lqRPpgZ1mv-O/image.png\">image.png</a> </p>\n<div class=\"message_inline_image\"><a href=\"/user_uploads/2/65/HjqKFHPE6h7_lqRPpgZ1mv-O/image.png\" title=\"image.png\"><img src=\"/user_uploads/2/65/HjqKFHPE6h7_lqRPpgZ1mv-O/image.png\"></a></div><blockquote>\n<p>\"Is this immediately recognized as a globe\"</p>\n</blockquote>\n<p>For whom exactly? For North Americans? What if the icon is a pink color?</p>\n<p>Here is the example of the Material Design Globe which I'm trying instead of wired version: <a href=\"/user_uploads/2/f3/jlPD4gixKlFnQAgVvOh74Ya_/image.png\">image.png</a> </p>\n<div class=\"message_inline_image\"><a href=\"/user_uploads/2/f3/jlPD4gixKlFnQAgVvOh74Ya_/image.png\" title=\"image.png\"><img src=\"/user_uploads/2/f3/jlPD4gixKlFnQAgVvOh74Ya_/image.png\"></a></div><p>And it is not 100% recognizable because the color of the land is blue and the color of the water is grey (transparent)</p>\n<p>I don't think we have to fight for \"the best recognition ever\" because these icons are context related. <br>\nI thought we should avoid if an icon of a public stream could be confused with regular stream or private stream.<br>\nAside from that any icon a person spends 3 days staring would be \"recognizable for him\".</p>\n<p>Here is the icon of Google Chrome <a href=\"/user_uploads/2/c8/aN3aJuN3kj6Yh4RJF5UHEy7a/image.png\">image.png</a>. Can anybody tell me out of their head what is the meaning of it and what is the context? I'm sure you saw that at least once... Not an easy task.</p>\n<div class=\"message_inline_image\"><a href=\"/user_uploads/2/c8/aN3aJuN3kj6Yh4RJF5UHEy7a/image.png\" title=\"image.png\"><img src=\"/user_uploads/2/c8/aN3aJuN3kj6Yh4RJF5UHEy7a/image.png\"></a></div><p>It feels like we have 2 choices here:</p>\n<ol>\n<li>\"Abstract globe\" with minimum elements: <a href=\"/user_uploads/2/c3/e8IfH_en9qdcXb0abpiKdsIn/image.png\">image.png</a> - Feather icons. Currently is used inside Zulip mobile app for \"All messages\" for some reason.<div class=\"message_inline_image\"><a href=\"/user_uploads/2/c3/e8IfH_en9qdcXb0abpiKdsIn/image.png\" title=\"image.png\"><img src=\"/user_uploads/2/c3/e8IfH_en9qdcXb0abpiKdsIn/image.png\"></a></div></li>\n<li>\"a disk with a scribble inside\" - pick any but probably north americans should recognize it?</li>\n</ol>",
        "id": 1346663,
        "sender_full_name": "Vlad Korobov",
        "timestamp": 1647486147
    },
    {
        "content": "<p><span class=\"user-mention silent\" data-user-id=\"22433\">Vlad Korobov</span> <a href=\"#narrow/stream/101-design/topic/globe.20icon.20for.20world-public.20streams/near/1346663\">said</a>:</p>\n<blockquote>\n<ol>\n<li>\"Abstract globe\" with minimum elements: <a href=\"/user_uploads/2/c3/e8IfH_en9qdcXb0abpiKdsIn/image.png\">image.png</a> - Feather icons. Currently is used inside Zulip mobile app for \"All messages\" for some reason.</li>\n</ol>\n</blockquote>\n<p>I'd certainly be happy to change that to something else.</p>\n<p>It looks like the current icon on web for \"All messages\" is a sort of \"list\" icon: <a href=\"/user_uploads/2/83/Jdu2wUL9yxXV42-cm1z_CLmH/image.png\">image.png</a></p>\n<div class=\"message_inline_image\"><a href=\"/user_uploads/2/83/Jdu2wUL9yxXV42-cm1z_CLmH/image.png\" title=\"image.png\"><img src=\"/user_uploads/2/83/Jdu2wUL9yxXV42-cm1z_CLmH/image.png\"></a></div><p>I'd be happy to switch to that on mobile. I don't recall what it used to be on web, but I don't think it was that, or else we'd have switched to it long ago.</p>",
        "id": 1346685,
        "sender_full_name": "Greg Price",
        "timestamp": 1647488153
    },
    {
        "content": "<p>We switched to the list icon from the home icon.</p>",
        "id": 1346834,
        "sender_full_name": "Aman (amanagr)",
        "timestamp": 1647519618
    },
    {
        "content": "<p><a href=\"/user_uploads/2/84/K0ER99EWZnCjG-mTF8-jt_nf/Screenshot-2022-03-17-at-5.56.15-PM.png\">Screenshot-2022-03-17-at-5.56.15-PM.png</a> </p>\n<div class=\"message_inline_image\"><a href=\"/user_uploads/2/84/K0ER99EWZnCjG-mTF8-jt_nf/Screenshot-2022-03-17-at-5.56.15-PM.png\" title=\"Screenshot-2022-03-17-at-5.56.15-PM.png\"><img src=\"/user_uploads/2/84/K0ER99EWZnCjG-mTF8-jt_nf/Screenshot-2022-03-17-at-5.56.15-PM.png\"></a></div><p>This icon looks like a good alternative to me as well.</p>",
        "id": 1346835,
        "sender_full_name": "Aman (amanagr)",
        "timestamp": 1647520032
    },
    {
        "content": "<p><span class=\"user-mention silent\" data-user-id=\"5140\">Aman Agrawal (amanagr)</span> <a href=\"#narrow/stream/101-design/topic/globe.20icon.20for.20world-public.20streams/near/1346834\">said</a>:</p>\n<blockquote>\n<p>We switched to the list icon from the home icon.</p>\n</blockquote>\n<p>Ah, right.</p>\n<p>Yeah, when it was a \"home\" icon, we didn't want to use that in mobile because we felt it would put too much emphasis on the all-messages view -- the real \"home\" view for the mobile app is the screen showing your unreads.</p>",
        "id": 1347020,
        "sender_full_name": "Greg Price",
        "timestamp": 1647542335
    },
    {
        "content": "<p>Switching to the list icon for \"All messages\" on mobile sounds like a nice improvement in consistency of experience. <span class=\"user-mention\" data-user-id=\"2187\">@Greg Price</span> should I file an issue for it?</p>",
        "id": 1347024,
        "sender_full_name": "Alya Abbott",
        "timestamp": 1647542455
    },
    {
        "content": "<p>I'd say yes except that I just started writing one myself <span aria-label=\"smile\" class=\"emoji emoji-1f642\" role=\"img\" title=\"smile\">:smile:</span> Thanks!</p>",
        "id": 1347025,
        "sender_full_name": "Greg Price",
        "timestamp": 1647542484
    },
    {
        "content": "<p><a href=\"https://github.com/zulip/zulip-mobile/pull/5303\">#M5303</a></p>",
        "id": 1347030,
        "sender_full_name": "Greg Price",
        "timestamp": 1647542595
    },
    {
        "content": "<p>The Feature icon isn't working for me -- having part of Central/North America results in a much less distinctive shape:<br>\n<a href=\"user_uploads/2/40/DwwMz2Sjb3FmnyqkrRK0X_JY/image.png\">https://chat.zulip.org/user_uploads/2/40/DwwMz2Sjb3FmnyqkrRK0X_JY/image.png</a></p>\n<div class=\"message_inline_image\"><a href=\"user_uploads/2/40/DwwMz2Sjb3FmnyqkrRK0X_JY/image.png\" title=\"https://chat.zulip.org/user_uploads/2/40/DwwMz2Sjb3FmnyqkrRK0X_JY/image.png\"><img src=\"user_uploads/2/40/DwwMz2Sjb3FmnyqkrRK0X_JY/image.png\"></a></div><p>If we want a different continent than North America, I like Font Awesome 6 one, because Africa is a distinctive shape.</p>\n<p><a href=\"/user_uploads/2/da/NAizupc-N7p2E-gV21f2-Jc0/image.png\">image.png</a> </p>\n<div class=\"message_inline_image\"><a href=\"/user_uploads/2/da/NAizupc-N7p2E-gV21f2-Jc0/image.png\" title=\"image.png\"><img src=\"/user_uploads/2/da/NAizupc-N7p2E-gV21f2-Jc0/image.png\"></a></div><p>I think that's <a href=\"https://fontawesome.com/icons/earth-africa\">https://fontawesome.com/icons/earth-africa</a>. However, we can only use the \"solid\" variant from Font Awesome specifically because their other variants are not OSS licensed.</p>",
        "id": 1347352,
        "sender_full_name": "Tim Abbott",
        "timestamp": 1647557230
    },
    {
        "content": "<p>Assume the jitsi link in there is accidental? (edit: now removed)</p>\n<p>Though probably interesting to figure out how it happened.</p>",
        "id": 1347354,
        "sender_full_name": "Alex Vandiver",
        "timestamp": 1647557321
    },
    {
        "content": "<p>And yeah, what I was saying is that the Font Awesome 4 which shows North America is I think the best on the \"Distinctive shape\" axis:<br>\n<a href=\"user_uploads/2/1b/J71hFI1gUOHEBTSr0sARcIU0/image.png\">https://chat.zulip.org/user_uploads/2/1b/J71hFI1gUOHEBTSr0sARcIU0/image.png</a></p>\n<div class=\"message_inline_image\"><a href=\"user_uploads/2/1b/J71hFI1gUOHEBTSr0sARcIU0/image.png\" title=\"https://chat.zulip.org/user_uploads/2/1b/J71hFI1gUOHEBTSr0sARcIU0/image.png\"><img src=\"user_uploads/2/1b/J71hFI1gUOHEBTSr0sARcIU0/image.png\"></a></div><p>We can pick a different one because we'd prefer to not be North America centric, but I do think a visually distinctive part of Earth geography is much better than a less recognizable one.</p>",
        "id": 1347355,
        "sender_full_name": "Tim Abbott",
        "timestamp": 1647557328
    },
    {
        "content": "<p><span class=\"user-mention silent\" data-user-id=\"12178\">Alex Vandiver</span> <a href=\"#narrow/stream/101-design/topic/globe.20icon.20for.20world-public.20streams/near/1347354\">said</a>:</p>\n<blockquote>\n<p>Assume the jitsi link in there is accidental? (edit: now removed)</p>\n<p>Though probably interesting to figure out how it happened.</p>\n</blockquote>\n<p>I'm pretty sure this was just because the video call button is next to the preview button and I misclicked.</p>",
        "id": 1347356,
        "sender_full_name": "Tim Abbott",
        "timestamp": 1647557397
    },
    {
        "content": "<p>Which is an argument for moving the preview button someplace not adjacent to things that alter the contents of the box</p>",
        "id": 1347358,
        "sender_full_name": "Alex Vandiver",
        "timestamp": 1647557432
    },
    {
        "content": "<p>Yeah, but this is the first time I've seen this happen in a few years of having the preview button between two things, so I wouldn't assume it's worth making any change motivated by a single instance of that <span aria-label=\"smile\" class=\"emoji emoji-1f642\" role=\"img\" title=\"smile\">:smile:</span></p>",
        "id": 1347360,
        "sender_full_name": "Tim Abbott",
        "timestamp": 1647557489
    },
    {
        "content": "<p>No, but I think it's also a clear example of \"does a different thing than what it is surrounded by.\"</p>\n<p>Anyways, this is a tangent, and the latest mockups I've seen <em>do</em> move it out of the insert-things-in-the-box area.</p>",
        "id": 1347369,
        "sender_full_name": "Alex Vandiver",
        "timestamp": 1647557825
    },
    {
        "content": "<p>How about this one? <a href=\"/user_uploads/2/74/oByVYaFfdUtGorWYIJpwVUXu/image.png\">image.png</a></p>\n<div class=\"message_inline_image\"><a href=\"/user_uploads/2/74/oByVYaFfdUtGorWYIJpwVUXu/image.png\" title=\"image.png\"><img src=\"/user_uploads/2/74/oByVYaFfdUtGorWYIJpwVUXu/image.png\"></a></div>",
        "id": 1347470,
        "sender_full_name": "Vlad Korobov",
        "timestamp": 1647562071
    },
    {
        "content": "<p>I like the concept, but that image has a lot of detail --  I'd want to see how it comes out at a small size.</p>",
        "id": 1347474,
        "sender_full_name": "Greg Price",
        "timestamp": 1647562165
    },
    {
        "content": "<p>I like that one!  I'd expect it to work at a small size after zooming it in the Zoom lightbox, but agree that it needs testing.</p>",
        "id": 1347482,
        "sender_full_name": "Tim Abbott",
        "timestamp": 1647562365
    },
    {
        "content": "<p><a href=\"/user_uploads/2/9c/Zh4aUxV6NpQOEqkf8opBH4K2/image.png\">image.png</a></p>\n<div class=\"message_inline_image\"><a href=\"/user_uploads/2/9c/Zh4aUxV6NpQOEqkf8opBH4K2/image.png\" title=\"image.png\"><img src=\"/user_uploads/2/9c/Zh4aUxV6NpQOEqkf8opBH4K2/image.png\"></a></div>",
        "id": 1347503,
        "sender_full_name": "Vlad Korobov",
        "timestamp": 1647563397
    },
    {
        "content": "<p>Yeah, I think that will work. Here's a crop around that icon, after zooming to around the size the real thing has on my screen: <a href=\"/user_uploads/2/50/d2l93HnepFz3B_Z-FvFnR_-D/image.png\">image.png</a></p>\n<div class=\"message_inline_image\"><a href=\"/user_uploads/2/50/d2l93HnepFz3B_Z-FvFnR_-D/image.png\" title=\"image.png\"><img src=\"/user_uploads/2/50/d2l93HnepFz3B_Z-FvFnR_-D/image.png\"></a></div>",
        "id": 1347510,
        "sender_full_name": "Greg Price",
        "timestamp": 1647563702
    },
    {
        "content": "<p>you can see it in context in 100% scale here <a href=\"https://www.figma.com/proto/jbNOiBWvbtLuHaiTj4CW0G/Zulip-2022?page-id=1392%3A88715&amp;node-id=1392%3A95137&amp;viewport=399%2C48%2C0.27&amp;scaling=min-zoom&amp;starting-point-node-id=1392%3A95137\">https://www.figma.com/proto/jbNOiBWvbtLuHaiTj4CW0G/Zulip-2022?page-id=1392%3A88715&amp;node-id=1392%3A95137&amp;viewport=399%2C48%2C0.27&amp;scaling=min-zoom&amp;starting-point-node-id=1392%3A95137</a></p>",
        "id": 1347517,
        "sender_full_name": "Vlad Korobov",
        "timestamp": 1647563910
    },
    {
        "content": "<p>Yeah, I think that'll work too. What's the icon's licensing situation?</p>",
        "id": 1347518,
        "sender_full_name": "Tim Abbott",
        "timestamp": 1647563912
    },
    {
        "content": "<p><a href=\"https://github.com/ionic-team/ionicons/blob/main/LICENSE\">https://github.com/ionic-team/ionicons/blob/main/LICENSE</a></p>",
        "id": 1347566,
        "sender_full_name": "Vlad Korobov",
        "timestamp": 1647575440
    },
    {
        "content": "<p>Works for me!</p>",
        "id": 1347837,
        "sender_full_name": "Alya Abbott",
        "timestamp": 1647625681
    },
    {
        "content": "<p>Great, <span class=\"user-mention\" data-user-id=\"5140\">@Aman Agrawal (amanagr)</span> want to put together a quick PR switching to that icon so we can test it? <span class=\"user-mention\" data-user-id=\"22433\">@Vlad Korobov</span> it'd be helpful if you can provide the direct link to the SVG source.</p>",
        "id": 1347867,
        "sender_full_name": "Tim Abbott",
        "timestamp": 1647626632
    },
    {
        "content": "<p><a href=\"/user_uploads/2/8b/rcND476dYjM79N4U2PsOcsgw/icon-globe.svg\">icon-globe.svg</a></p>",
        "id": 1348164,
        "sender_full_name": "Vlad Korobov",
        "timestamp": 1647644035
    },
    {
        "content": "<p>I got to tune it  a bit, so its not actually 100% original</p>",
        "id": 1348165,
        "sender_full_name": "Vlad Korobov",
        "timestamp": 1647644053
    },
    {
        "content": "<p>Please still provide a link to the original SVG source, and if changes were necessary, explain what you changed. It’s important that we have a record of these things, so we can document the licensing and attribution information in <code>docs/THIRDPARTY</code>, and so we can replicate the changes in the future if it becomes necessary.</p>",
        "id": 1348181,
        "sender_full_name": "Anders Kaseorg",
        "timestamp": 1647645704
    },
    {
        "content": "<p>Globe icon is from this set <a href=\"https://github.com/ionic-team/ionicons/blob/main/LICENSE\">https://github.com/ionic-team/ionicons/blob/main/LICENSE</a><br>\nThis is the direct link to the image <a href=\"https://unpkg.com/ionicons@5.5.2/dist/svg/earth-sharp.svg\">https://unpkg.com/ionicons@5.5.2/dist/svg/earth-sharp.svg</a><br>\nI changed the outline around the globe.</p>\n<p>I don't want to describe every change I made to every open source icon. If you guys define what is the amount of change required to make something legally not using third party icon I would perform such actions.<br>\nOnce we be in the implementation phase I'll check every icon if it was an original one or from a particular package and make a note in Figma about it.</p>",
        "id": 1348255,
        "sender_full_name": "Vlad Korobov",
        "timestamp": 1647650828
    },
    {
        "content": "<p><a href=\"https://github.com/zulip/zulip/blob/main/docs/THIRDPARTY\">https://github.com/zulip/zulip/blob/main/docs/THIRDPARTY</a> shows the lvel of detail we need for attribution; figured I'd show a link to make it easy to view.</p>",
        "id": 1348256,
        "sender_full_name": "Tim Abbott",
        "timestamp": 1647650957
    },
    {
        "content": "<p>(And then a few human-readable notes to specify what we did is all we need for reproducibility in the future)</p>",
        "id": 1348257,
        "sender_full_name": "Tim Abbott",
        "timestamp": 1647650981
    },
    {
        "content": "<p>I see there are links to some set of files but I don't see an example of reproducibility of an icon</p>",
        "id": 1348410,
        "sender_full_name": "Vlad Korobov",
        "timestamp": 1647716222
    },
    {
        "content": "<p>Almost all of our icons that we didn’t make ourselves are referenced directly from NPM packages, so we don’t need to keep manual copies. The one exception is static/assets/icons/ellipsis-v-solid.svg, which has an entry in docs/THIRDPARTY.</p>\n<div class=\"codehilite\" data-code-language=\"Debian Control file\"><pre><span></span><code><span class=\"k\">Files</span><span class=\"w\">: </span><span class=\"s\">static/assets/icons/ellipsis-v-solid.svg</span>\n<span class=\"k\">Copyright</span><span class=\"w\">: </span><span class=\"s\">2017 Fonticons, Inc.</span>\n<span class=\"k\">License</span><span class=\"w\">: </span><span class=\"s\">CC-BY-4.0</span>\n<span class=\"k\">Comment</span><span class=\"w\">: </span><span class=\"s\">This icon is picked from Version 5.13.0 of Font Awesome</span>\n</code></pre></div>\n<p>(And really we should fix that one to be an NPM reference too.)</p>",
        "id": 1348444,
        "sender_full_name": "Anders Kaseorg",
        "timestamp": 1647731256
    },
    {
        "content": "<blockquote>\n<p>If you guys define what is the amount of change required to make something legally not using third party icon I would perform such actions.</p>\n</blockquote>\n<p>If you change someone else’s work, you’ve created a derivative work, so you need to respect their copyright and license. There’s no amount of change that absolves you of this responsibility. But it’s typically not hard for open-source licenses.</p>",
        "id": 1348447,
        "sender_full_name": "Anders Kaseorg",
        "timestamp": 1647733180
    },
    {
        "content": "<p>If you tell us that an icon came from <a href=\"https://unpkg.com/ionicons@5.5.2/dist/svg/earth-sharp.svg\">https://unpkg.com/ionicons@5.5.2/dist/svg/earth-sharp.svg</a> (actually isn’t it <a href=\"https://unpkg.com/ionicons@5.5.2/dist/svg/earth.svg\">earth.svg</a>?), and that you slightly thickened the border, that’s enough information for us to easily look up the legal information when we need to record it during implementation. It’s also just generally useful to know where we might find other icons in a similar style and how we might want to modify them to match.</p>",
        "id": 1348451,
        "sender_full_name": "Anders Kaseorg",
        "timestamp": 1647733955
    },
    {
        "content": "<p>Opened <a href=\"https://github.com/zulip/zulip/pull/21491\">#21491</a></p>",
        "id": 1348588,
        "sender_full_name": "Aman (amanagr)",
        "timestamp": 1647796085
    },
    {
        "content": "<p><a href=\"/user_uploads/2/1b/GtMZy_n55qbhtnSNlt_Viq9z/image.png\">image.png</a></p>\n<div class=\"message_inline_image\"><a href=\"/user_uploads/2/1b/GtMZy_n55qbhtnSNlt_Viq9z/image.png\" title=\"image.png\"><img src=\"/user_uploads/2/1b/GtMZy_n55qbhtnSNlt_Viq9z/image.png\"></a></div>",
        "id": 1348590,
        "sender_full_name": "Aman (amanagr)",
        "timestamp": 1647796102
    },
    {
        "content": "<p>I'm test-deploying this revised globe icon now.</p>",
        "id": 1349567,
        "sender_full_name": "Tim Abbott",
        "timestamp": 1647912119
    },
    {
        "content": "<p>Due to a caching issue, you need to shift-reload your browser in order to see the revised icon that's been deployed here since yesterday.</p>",
        "id": 1350276,
        "sender_full_name": "Tim Abbott",
        "timestamp": 1647988001
    },
    {
        "content": "<p>Feedback on how the icon is working for folks would be much appreciated, since deciding what icon to go with for 5.0 is one of our few remaining things to do before we release.</p>",
        "id": 1350279,
        "sender_full_name": "Tim Abbott",
        "timestamp": 1647988040
    },
    {
        "content": "<p>Just shift-reloaded and I see it. I like it! Here's how it comes out on my screen: <a href=\"/user_uploads/2/e2/ygUh2SiuZgVZOwXSWR5iy-zp/image.png\">image.png</a></p>\n<div class=\"message_inline_image\"><a href=\"/user_uploads/2/e2/ygUh2SiuZgVZOwXSWR5iy-zp/image.png\" title=\"image.png\"><img src=\"/user_uploads/2/e2/ygUh2SiuZgVZOwXSWR5iy-zp/image.png\"></a></div><p>I think that's pretty legible, as icons go.</p>",
        "id": 1350334,
        "sender_full_name": "Greg Price",
        "timestamp": 1647989375
    },
    {
        "content": "<p>One thing that seems to be missing and would be good to add is a tooltip explaining what it means, so you can find out by hovering if you don't know.</p>\n<p>I'm not getting such a tooltip when I hover in the left sidebar, or in the top bar. I <em>do</em> see one in the recipient header, so that's good -- but I think the left sidebar is probably a more salient place for people to look than there.</p>",
        "id": 1350337,
        "sender_full_name": "Greg Price",
        "timestamp": 1647989483
    },
    {
        "content": "<p>Similarly a tooltip would be good where it appears in stream settings: <a href=\"/user_uploads/2/b7/r5D7vBHVlyXDDTzrjteQtuS0/image.png\">image.png</a></p>\n<div class=\"message_inline_image\"><a href=\"/user_uploads/2/b7/r5D7vBHVlyXDDTzrjteQtuS0/image.png\" title=\"image.png\"><img src=\"/user_uploads/2/b7/r5D7vBHVlyXDDTzrjteQtuS0/image.png\"></a></div>",
        "id": 1350338,
        "sender_full_name": "Greg Price",
        "timestamp": 1647989530
    },
    {
        "content": "<p>Yeah, I think this icon works and doesn't have the \"language icon\" confusion we have with what's currently there, so I'll integrate this.</p>",
        "id": 1350362,
        "sender_full_name": "Tim Abbott",
        "timestamp": 1647990540
    },
    {
        "content": "<p>I agree those tooltip details would be nice to improve.</p>",
        "id": 1350363,
        "sender_full_name": "Tim Abbott",
        "timestamp": 1647990560
    },
    {
        "content": "<p>Do we want to do some cache-busting thing to deal with the fact that folks need to reload to see the new icon? I expect that to be a widespread issue for folks in the organizations that have already started testing web-public streams.</p>",
        "id": 1350378,
        "sender_full_name": "Tim Abbott",
        "timestamp": 1647991346
    },
    {
        "content": "<p>I think the simplest thing would be to rename the icon file from <code>globe.svg</code> to <code>web-public-globe.svg</code>, or similar.</p>",
        "id": 1350379,
        "sender_full_name": "Tim Abbott",
        "timestamp": 1647991361
    },
    {
        "content": "<p><span class=\"user-mention silent\" data-user-id=\"9808\">Yash RE</span> <a href=\"#narrow/stream/101-design/topic/globe.20icon.20for.20world-public.20streams/near/1337642\">said</a>:</p>\n<blockquote>\n<p>The icon is misaligned and not colored in the navbar.</p>\n</blockquote>\n<div class=\"message_inline_image\"><a href=\"/user_uploads/2/91/TIRhzQ5YPrPr5N13jpOsiCoY/image.png\"><img src=\"/user_uploads/2/91/TIRhzQ5YPrPr5N13jpOsiCoY/image.png\"></a></div>",
        "id": 1350494,
        "sender_full_name": "Yash RE",
        "timestamp": 1648004894
    },
    {
        "content": "<p>It's possible the main issue is just that we should decrease its size there?  Not sure, but agreed that needs to be fixed.</p>",
        "id": 1350498,
        "sender_full_name": "Tim Abbott",
        "timestamp": 1648005271
    },
    {
        "content": "<p>I'd just like to chime in and say that I think the new globe icon looks <em>so</em> much better than the grid based one of the last few weeks. Nice work.</p>",
        "id": 1350839,
        "sender_full_name": "Austin Riba",
        "timestamp": 1648054952
    },
    {
        "content": "<p>Testing design with people is the very right activity to do <span aria-label=\"smile\" class=\"emoji emoji-1f642\" role=\"img\" title=\"smile\">:smile:</span></p>",
        "id": 1350871,
        "sender_full_name": "Vlad Korobov",
        "timestamp": 1648056431
    },
    {
        "content": "<p>Happy to split this to another topic, but in the context of zulip-terminal I've been looking for a web-public unicode character that's reliable for \"typical\" terminals which suits the same intent as here. This criteria means no emoji and also likely avoiding some characters that appear to have dual-width.<br>\n(this pertains to <a class=\"stream-topic\" data-stream-id=\"206\" href=\"/#narrow/stream/206-zulip-terminal/topic/Web.20public.20marker.20.23T1135.2F.23T712.2F.23T1177\">#zulip-terminal &gt; Web public marker #T1135/#T712/#T1177</a>)</p>",
        "id": 1351227,
        "sender_full_name": "Neil Pilgrim (neiljp)",
        "timestamp": 1648074437
    },
    {
        "content": "<p>10 messages were moved from this topic to <a class=\"stream-topic\" data-stream-id=\"206\" href=\"/#narrow/stream/206-zulip-terminal/topic/Web.20public.20marker.20.23T1135.2F.23T712.2F.23T1177\">#zulip-terminal &gt; Web public marker #T1135/#T712/#T1177</a> by <span class=\"user-mention silent\" data-user-id=\"2187\">Greg Price</span>.</p>",
        "id": 1351245,
        "sender_full_name": "Notification Bot",
        "timestamp": 1648075962
    },
    {
        "content": "<p><span class=\"user-mention silent\" data-user-id=\"7\">Tim Abbott</span> <a href=\"#narrow/stream/101-design/topic/globe.20icon.20for.20world-public.20streams/near/1350498\">said</a>:</p>\n<blockquote>\n<p>It's possible the main issue is just that we should decrease its size there?  Not sure, but agreed that needs to be fixed.</p>\n</blockquote>\n<p>I recall we changed the alignment of it from some previous discussion.</p>\n<p><a href=\"/user_uploads/2/c8/AG_4mBTx6hPf5bvq4woBoxMF/Screenshot-2022-03-24-at-1.45.31-PM.png\">Screenshot-2022-03-24-at-1.45.31-PM.png</a></p>\n<div class=\"message_inline_image\"><a href=\"/user_uploads/2/c8/AG_4mBTx6hPf5bvq4woBoxMF/Screenshot-2022-03-24-at-1.45.31-PM.png\" title=\"Screenshot-2022-03-24-at-1.45.31-PM.png\"><img src=\"/user_uploads/2/c8/AG_4mBTx6hPf5bvq4woBoxMF/Screenshot-2022-03-24-at-1.45.31-PM.png\"></a></div>",
        "id": 1351575,
        "sender_full_name": "Aman (amanagr)",
        "timestamp": 1648109780
    },
    {
        "content": "<p>Do we want to align it lower ?</p>",
        "id": 1351576,
        "sender_full_name": "Aman (amanagr)",
        "timestamp": 1648109800
    },
    {
        "content": "<p>Yes</p>",
        "id": 1351735,
        "sender_full_name": "Vlad Korobov",
        "timestamp": 1648120484
    },
    {
        "content": "<p><span class=\"user-mention\" data-user-id=\"5140\">@Aman Agrawal (amanagr)</span> are you planning to tweak this? <span class=\"user-mention\" data-user-id=\"19257\">@Alya Abbott</span> might be worth your doing an audit for other places where we might want to adjust styling slightly, e.g. the compose box spacing is also a little tight:</p>\n<p><a href=\"/user_uploads/2/2f/5RlQojgMtG0IF36xX5w4NLgs/image.png\">image.png</a></p>\n<div class=\"message_inline_image\"><a href=\"/user_uploads/2/2f/5RlQojgMtG0IF36xX5w4NLgs/image.png\" title=\"image.png\"><img src=\"/user_uploads/2/2f/5RlQojgMtG0IF36xX5w4NLgs/image.png\"></a></div>",
        "id": 1352250,
        "sender_full_name": "Tim Abbott",
        "timestamp": 1648159844
    },
    {
        "content": "<p>This detail is one of the few classes of changes I'll gladly merge between 5.0-rc2 and the final release.</p>",
        "id": 1352251,
        "sender_full_name": "Tim Abbott",
        "timestamp": 1648159864
    },
    {
        "content": "<p>Yeah, the globe definitely looks to high in the top bar. It's less noticeable with other icons, but I think those are too high as well. The vertical alignment should look the same there as in the left sidebar.</p>\n<p><a href=\"/user_uploads/2/97/IQSDkv_ianV-sPWTnSaG-5OV/Zulip_-_Zulip_Community.png\">Zulip_-_Zulip_Community.png</a></p>\n<div class=\"message_inline_image\"><a href=\"/user_uploads/2/97/IQSDkv_ianV-sPWTnSaG-5OV/Zulip_-_Zulip_Community.png\" title=\"Zulip_-_Zulip_Community.png\"><img src=\"/user_uploads/2/97/IQSDkv_ianV-sPWTnSaG-5OV/Zulip_-_Zulip_Community.png\"></a></div>",
        "id": 1352340,
        "sender_full_name": "Alya Abbott",
        "timestamp": 1648163536
    },
    {
        "content": "<p>Agreed regarding compose box horizontal spacing as well.</p>",
        "id": 1352342,
        "sender_full_name": "Alya Abbott",
        "timestamp": 1648163670
    },
    {
        "content": "<p>Hmm, the lock in the compose box definitely looks higher than in the left sidebar.</p>\n<p><a href=\"/user_uploads/2/b9/OD-Pq-xBydwBvs6yt8F2mWQy/Screen-Shot-2022-03-24-at-4.45.07-PM.png\">Screen-Shot-2022-03-24-at-4.45.07-PM.png</a></p>\n<div class=\"message_inline_image\"><a href=\"/user_uploads/2/b9/OD-Pq-xBydwBvs6yt8F2mWQy/Screen-Shot-2022-03-24-at-4.45.07-PM.png\" title=\"Screen-Shot-2022-03-24-at-4.45.07-PM.png\"><img src=\"/user_uploads/2/b9/OD-Pq-xBydwBvs6yt8F2mWQy/Screen-Shot-2022-03-24-at-4.45.07-PM.png\"></a></div>",
        "id": 1352368,
        "sender_full_name": "Alya Abbott",
        "timestamp": 1648165573
    },
    {
        "content": "<p><a href=\"/user_uploads/2/f7/TC1ILz7DPKzXCOIZ6VvlwNaE/Screenshot-2022-03-25-at-12.49.04-PM.png\">Screenshot-2022-03-25-at-12.49.04-PM.png</a> <a href=\"/user_uploads/2/f8/J_5TL-A243yfngXOkeYhPvmx/Screenshot-2022-03-25-at-12.49.16-PM.png\">Screenshot-2022-03-25-at-12.49.16-PM.png</a></p>\n<div class=\"message_inline_image\"><a href=\"/user_uploads/2/f7/TC1ILz7DPKzXCOIZ6VvlwNaE/Screenshot-2022-03-25-at-12.49.04-PM.png\" title=\"Screenshot-2022-03-25-at-12.49.04-PM.png\"><img src=\"/user_uploads/2/f7/TC1ILz7DPKzXCOIZ6VvlwNaE/Screenshot-2022-03-25-at-12.49.04-PM.png\"></a></div><div class=\"message_inline_image\"><a href=\"/user_uploads/2/f8/J_5TL-A243yfngXOkeYhPvmx/Screenshot-2022-03-25-at-12.49.16-PM.png\" title=\"Screenshot-2022-03-25-at-12.49.16-PM.png\"><img src=\"/user_uploads/2/f8/J_5TL-A243yfngXOkeYhPvmx/Screenshot-2022-03-25-at-12.49.16-PM.png\"></a></div>",
        "id": 1352665,
        "sender_full_name": "Aman (amanagr)",
        "timestamp": 1648193194
    },
    {
        "content": "<p>Opened <a href=\"https://github.com/zulip/zulip/pull/21553\">#21553</a></p>",
        "id": 1352666,
        "sender_full_name": "Aman (amanagr)",
        "timestamp": 1648193266
    }
]