[
    {
        "content": "<p><a href=\"/user_uploads/2/66/q8OGy0KIDIMnXg2HART1pRBv/Screenshot-2023-09-19-at-9.13.44-AM.png\">Screenshot-2023-09-19-at-9.13.44-AM.png</a><br>\nTo better differenciate group pm, should add a group PM icon there? <span class=\"user-mention\" data-user-id=\"22433\">@Vlad Korobov</span></p>\n<div class=\"message_inline_image\"><a href=\"/user_uploads/2/66/q8OGy0KIDIMnXg2HART1pRBv/Screenshot-2023-09-19-at-9.13.44-AM.png\" title=\"Screenshot-2023-09-19-at-9.13.44-AM.png\"><img src=\"/user_uploads/2/66/q8OGy0KIDIMnXg2HART1pRBv/Screenshot-2023-09-19-at-9.13.44-AM.png\"></a></div>",
        "id": 1642680,
        "sender_full_name": "Aman (amanagr)",
        "timestamp": 1695095114
    },
    {
        "content": "<p>Based on <a href=\"https://github.com/zulip/zulip/pull/26770#issuecomment-1724226257\">Tim's comment</a>:<br>\n<a href=\"/user_uploads/2/81/0J1KuQyMyYWT4hHbzltvxNq0/Screenshot-2023-09-19-at-9.15.32-AM.png\">Screenshot-2023-09-19-at-9.15.32-AM.png</a></p>\n<div class=\"message_inline_image\"><a href=\"/user_uploads/2/81/0J1KuQyMyYWT4hHbzltvxNq0/Screenshot-2023-09-19-at-9.15.32-AM.png\" title=\"Screenshot-2023-09-19-at-9.15.32-AM.png\"><img src=\"/user_uploads/2/81/0J1KuQyMyYWT4hHbzltvxNq0/Screenshot-2023-09-19-at-9.15.32-AM.png\"></a></div>",
        "id": 1642681,
        "sender_full_name": "Aman (amanagr)",
        "timestamp": 1695095154
    },
    {
        "content": "<p>2 messages were moved here from <a class=\"stream-topic\" data-stream-id=\"101\" href=\"/#narrow/stream/101-design/topic/inbox.20view.20.2322408\">#design &gt; inbox view #22408</a> by <span class=\"user-mention silent\" data-user-id=\"5140\">Aman (amanagr)</span>.</p>",
        "id": 1642682,
        "sender_full_name": "Notification Bot",
        "timestamp": 1695095231
    },
    {
        "content": "<p>That sounds like a good design choice to me.</p>",
        "id": 1642790,
        "sender_full_name": "Karl Stolley",
        "timestamp": 1695129330
    },
    {
        "content": "<p>That seems like a satisfactory solution for this pass; I could also imagine doing something to create a bit more of a border between the rows but I think that can be a thing to consider in future design passes on the component.</p>",
        "id": 1643259,
        "sender_full_name": "Tim Abbott",
        "timestamp": 1695151833
    },
    {
        "content": "<p>In Recent conversations and the left sidebar, we us the group DM icon <em>instead of</em> presence indicators, rather than in addition. Should we do the same here?</p>",
        "id": 1643351,
        "sender_full_name": "Alya Abbott",
        "timestamp": 1695158421
    },
    {
        "content": "<p>The alignment in the screenshot looks off to me, and that might help.</p>",
        "id": 1643352,
        "sender_full_name": "Alya Abbott",
        "timestamp": 1695158445
    },
    {
        "content": "<p>Yeah I think that would help.</p>",
        "id": 1643364,
        "sender_full_name": "Tim Abbott",
        "timestamp": 1695160330
    }
]