[
    {
        "content": "<p>I'd like to work on <a href=\"https://github.com/zulip/zulip/pull/7889\" target=\"_blank\" title=\"https://github.com/zulip/zulip/pull/7889\">#7889</a> so thought we could probably discuss and decide on the final design here, <span class=\"user-mention\" data-user-email=\"rishig@zulipchat.com\" data-user-id=\"131\">@Rishi Gupta</span> ?</p>",
        "id": 409130,
        "sender_full_name": "Utkarsh Ajay Patil",
        "timestamp": 1514223774
    },
    {
        "content": "<p>Thanks! Though <a href=\"https://github.com/zulip/zulip/pull/7889\" target=\"_blank\" title=\"https://github.com/zulip/zulip/pull/7889\">#7889</a> is currently a part of another project; generally we try to use the <code>help wanted</code> label to signify which issues are unassigned / have gone through enough thought that they are ready to work on.</p>",
        "id": 409164,
        "sender_full_name": "Rishi Gupta",
        "timestamp": 1514225347
    },
    {
        "content": "<p>Alright cool <span class=\"emoji emoji-1f44d\" title=\"+1\">:+1:</span></p>",
        "id": 409172,
        "sender_full_name": "Utkarsh Ajay Patil",
        "timestamp": 1514225615
    }
]