[
    {
        "content": "<p>Is there a reason we don't hide the input box border in dark mode whereas we hide it in the light mode. I really like the light mode design without any bounding box. Would it look odd in dark mode like that? <span aria-label=\"thinking\" class=\"emoji emoji-1f914\" role=\"img\" title=\"thinking\">:thinking:</span> </p>\n<p>Screenshots for reference: <a href=\"/user_uploads/2/1c/ke_aa9QhuwPDHjHQW4WL4No6/image.png\">dark</a> <a href=\"/user_uploads/2/d9/cXzub06rr3y9ZletTAymor-z/image.png\">light</a></p>\n<div class=\"message_inline_image\"><a href=\"/user_uploads/2/1c/ke_aa9QhuwPDHjHQW4WL4No6/image.png\" title=\"dark\"><img src=\"/user_uploads/2/1c/ke_aa9QhuwPDHjHQW4WL4No6/image.png\"></a></div><div class=\"message_inline_image\"><a href=\"/user_uploads/2/d9/cXzub06rr3y9ZletTAymor-z/image.png\" title=\"light\"><img src=\"/user_uploads/2/d9/cXzub06rr3y9ZletTAymor-z/image.png\"></a></div>",
        "id": 1247626,
        "sender_full_name": "Dinesh Ch",
        "timestamp": 1629221214
    },
    {
        "content": "<p><code>Add another user</code> text will not be visible in that case.</p>",
        "id": 1247760,
        "sender_full_name": "Aman (amanagr)",
        "timestamp": 1629252034
    },
    {
        "content": "<p>Hmm, maybe we could use a brighter colour? But I'm unsure if it'll look good. <span aria-label=\"thinking\" class=\"emoji emoji-1f914\" role=\"img\" title=\"thinking\">:thinking:</span> </p>\n<p>(Has there been any discussion previously about this? Perhaps we resolved the current UI is better considering other options?)</p>",
        "id": 1248145,
        "sender_full_name": "Dinesh Ch",
        "timestamp": 1629380810
    },
    {
        "content": "<p><span class=\"user-mention\" data-user-id=\"13362\">@Dinesh Ch</span> I don't think there's been any recent discussion of it.  I have a vague recollection that the box was added when we ported the compose box to support the night theme to work around some problem, but don't recall what.</p>\n<p>I do think the inconsistency is a bit weird, but I'm not sure which direction is better.  We might want to start with just making the font a little more visible for the \"Add another user\", and then play with removing the box in the night theme.</p>",
        "id": 1253348,
        "sender_full_name": "Tim Abbott",
        "timestamp": 1631042042
    },
    {
        "content": "<p><span class=\"user-mention silent\" data-user-id=\"19257\">Alya Abbott</span> <a href=\"#narrow/stream/137-feedback/topic/narrow.20to.20topic.2Fpms.20when.20composing/near/1316232\">said</a>:</p>\n<blockquote>\n<p>The dark theme is probably more like what we had in mind?</p>\n</blockquote>\n<p>I think the dark theme variant is better, yeah.</p>",
        "id": 1316291,
        "sender_full_name": "Tim Abbott",
        "timestamp": 1643198783
    },
    {
        "content": "<p>This topic was moved here from <a class=\"stream-topic\" data-stream-id=\"137\" href=\"/#narrow/stream/137-feedback/topic/pm.20recipients.20input.20dark.20vs.20light.20mode\">#feedback &gt; pm recipients input dark vs light mode</a> by <span class=\"user-mention silent\" data-user-id=\"19257\">Alya Abbott</span></p>",
        "id": 1316571,
        "sender_full_name": "Notification Bot",
        "timestamp": 1643233693
    },
    {
        "content": "<p>This question came up again recently (context: <a class=\"stream-topic\" data-stream-id=\"137\" href=\"/#narrow/stream/137-feedback/topic/narrow.20to.20topic.2Fpms.20when.20composing\">#feedback &gt; narrow to topic/pms when composing</a> ). Thoughts?</p>\n<p>It looks like <span class=\"user-mention silent\" data-user-id=\"7\">Tim Abbott</span> had different intuition in August vs. looking it again today. :)</p>",
        "id": 1316574,
        "sender_full_name": "Alya Abbott",
        "timestamp": 1643233765
    },
    {
        "content": "<p>Yeah, I think ultimately we need to play with things to come to a clear conclusion; it's mostly a visual question and easier to discuss with screenshots than in the abstract.</p>",
        "id": 1316616,
        "sender_full_name": "Tim Abbott",
        "timestamp": 1643238975
    },
    {
        "content": "<p>Sure, it would be helpful to see screenshots/mockups where light mode is styled like dark mode, and/or where dark mode is styled like light mode. We should be thinking about this in conjunction with how to visually indicate <a class=\"stream-topic\" data-stream-id=\"137\" href=\"/#narrow/stream/137-feedback/topic/narrow.20to.20topic.2Fpms.20when.20composing\">#feedback &gt; narrow to topic/pms when composing</a> .</p>",
        "id": 1316621,
        "sender_full_name": "Alya Abbott",
        "timestamp": 1643239451
    },
    {
        "content": "<p>I can get to this once we finish other design decisions</p>",
        "id": 1316705,
        "sender_full_name": "Vlad Korobov",
        "timestamp": 1643255174
    }
]