[
    {
        "content": "<p>Are the profile/user popover actions not centered?</p>",
        "id": 292500,
        "sender_full_name": "Joshua Pan",
        "timestamp": 1507068964
    },
    {
        "content": "<p>Like the options below the user profile</p>",
        "id": 292501,
        "sender_full_name": "Joshua Pan",
        "timestamp": 1507068976
    },
    {
        "content": "<p><span class=\"user-mention\" data-user-email=\"joshuapan8@gmail.com\" data-user-id=\"857\">@Joshua Pan</span> can you explain what you mean with a screenshot?</p>",
        "id": 292502,
        "sender_full_name": "Tim Abbott",
        "timestamp": 1507068979
    },
    {
        "content": "<p>Oh, correct, those are not.</p>",
        "id": 292504,
        "sender_full_name": "Tim Abbott",
        "timestamp": 1507068987
    },
    {
        "content": "<p>Is that on purpose?</p>",
        "id": 292505,
        "sender_full_name": "Joshua Pan",
        "timestamp": 1507069002
    },
    {
        "content": "<p>Well, we want to have the icons on the sides aligned.  I think it'd be reasonable to center the block, though.</p>",
        "id": 292506,
        "sender_full_name": "Tim Abbott",
        "timestamp": 1507069022
    },
    {
        "content": "<p>I see. We don't necessarily have to center, but maybe move it to the right a few pixels</p>",
        "id": 292509,
        "sender_full_name": "Joshua Pan",
        "timestamp": 1507069059
    }
]