[
    {
        "content": "<p>For images that fail to load in spectator view due to rate limit restrictions or otherwise, we are planning to show this as part of <a href=\"https://github.com/zulip/zulip/pull/19840\">#19840</a></p>\n<p><a href=\"/user_uploads/2/a0/RROep10GMiBB1paXKC77iG8k/Screenshot-2021-11-02-at-7.54.37-PM.png\">Screenshot-2021-11-02-at-7.54.37-PM.png</a></p>\n<div class=\"message_inline_image\"><a href=\"/user_uploads/2/a0/RROep10GMiBB1paXKC77iG8k/Screenshot-2021-11-02-at-7.54.37-PM.png\" title=\"Screenshot-2021-11-02-at-7.54.37-PM.png\"><img src=\"/user_uploads/2/a0/RROep10GMiBB1paXKC77iG8k/Screenshot-2021-11-02-at-7.54.37-PM.png\"></a></div>",
        "id": 1275323,
        "sender_full_name": "Aman (amanagr)",
        "timestamp": 1635863347
    },
    {
        "content": "<p>Yeah, that looks good for this sort of rare corner case.</p>",
        "id": 1275508,
        "sender_full_name": "Tim Abbott",
        "timestamp": 1635882527
    }
]