[
    {
        "content": "<p>imo the \"Users join as\" is too prominent in our current invite modal, and puts the two options at too equal a level:<br>\n<a href=\"/user_uploads/2/5e/MdNQJlqZ5dwnbZehvlskPEKZ/pasted_image.png\" target=\"_blank\" title=\"pasted_image.png\">pasted image</a> </p>\n<p>What would folks think of </p>\n<div class=\"codehilite\"><pre><span></span>Emails    [      textbox      ]\n          [                   ]\n          [ ] Add as administrators\nCustom ...\n</pre></div>\n\n\n<p>where the <code>[ ]</code> is a checkbox?</p>\n<div class=\"message_inline_image\"><a href=\"/user_uploads/2/5e/MdNQJlqZ5dwnbZehvlskPEKZ/pasted_image.png\" target=\"_blank\" title=\"pasted image\"><img src=\"/user_uploads/2/5e/MdNQJlqZ5dwnbZehvlskPEKZ/pasted_image.png\"></a></div>",
        "id": 331583,
        "sender_full_name": "Rishi Gupta",
        "timestamp": 1511139967
    },
    {
        "content": "<p>I think that's probably better, yeah.</p>",
        "id": 331585,
        "sender_full_name": "Tim Abbott",
        "timestamp": 1511140111
    },
    {
        "content": "<p>cool, opened as <a href=\"https://github.com/zulip/zulip/pull/7446\" target=\"_blank\" title=\"https://github.com/zulip/zulip/pull/7446\">#7446</a>.</p>",
        "id": 331586,
        "sender_full_name": "Rishi Gupta",
        "timestamp": 1511141039
    },
    {
        "content": "<p>How does this look?<a href=\"/user_uploads/2/66/oV5CciRaTxwOlJ2r-SSn17cL/Screen-Shot-2017-11-20-at-10.36.02-AM.png\" target=\"_blank\" title=\"Screen-Shot-2017-11-20-at-10.36.02-AM.png\">Screen-Shot-2017-11-20-at-10.36.02-AM.png</a></p>\n<div class=\"message_inline_image\"><a href=\"/user_uploads/2/66/oV5CciRaTxwOlJ2r-SSn17cL/Screen-Shot-2017-11-20-at-10.36.02-AM.png\" target=\"_blank\" title=\"Screen-Shot-2017-11-20-at-10.36.02-AM.png\"><img src=\"/user_uploads/2/66/oV5CciRaTxwOlJ2r-SSn17cL/Screen-Shot-2017-11-20-at-10.36.02-AM.png\"></a></div>",
        "id": 332417,
        "sender_full_name": "Chayce Heiberg",
        "timestamp": 1511203181
    },
    {
        "content": "<p><span class=\"user-mention\" data-user-email=\"theheibergproject@gmail.com\" data-user-id=\"3633\">@Chayce Heiberg</span> not bad; there's a nicer checkbox style that we use in the settings pages you might want to use.</p>",
        "id": 332455,
        "sender_full_name": "Tim Abbott",
        "timestamp": 1511204681
    },
    {
        "content": "<p><span class=\"user-mention\" data-user-email=\"tabbott@zulipchat.com\" data-user-id=\"7\">@Tim Abbott</span>  Oh wow I'm surprised I didn't see that. Thank you.</p>",
        "id": 332519,
        "sender_full_name": "Chayce Heiberg",
        "timestamp": 1511205843
    },
    {
        "content": "<p>hello guys, I wanted to know whether issue <a href=\"https://github.com/zulip/zulip/pull/7446\" target=\"_blank\" title=\"https://github.com/zulip/zulip/pull/7446\">#7446</a> still open.. Shall I work on it...?</p>",
        "id": 506354,
        "sender_full_name": "Raju Jha",
        "timestamp": 1519030814
    },
    {
        "content": "<p>Hey! Usually one should see the full comment history of an issue. The last comment is that \"this is in review\" so this means that someone has worked on it already and its almost complete.</p>",
        "id": 506358,
        "sender_full_name": "Rohitt Vashishtha",
        "timestamp": 1519031228
    },
    {
        "content": "<p>You should pick up some other issue :)</p>",
        "id": 506359,
        "sender_full_name": "Rohitt Vashishtha",
        "timestamp": 1519031239
    },
    {
        "content": "<p>Hey.<br>\nI recently opened a PR for this <a href=\"https://github.com/zulip/zulip/pull/9904\" target=\"_blank\" title=\"https://github.com/zulip/zulip/pull/9904\">#9904</a>. Could someone please review? Any feedback of the design would be appreciated.  <a href=\"/user_uploads/2/3c/kxXkcMvLlk2RVtNTq-J2GDf0/zulip_7446fix.png\" target=\"_blank\" title=\"zulip_7446fix.png\">zulip_7446fix.png</a></p>\n<div class=\"message_inline_image\"><a href=\"/user_uploads/2/3c/kxXkcMvLlk2RVtNTq-J2GDf0/zulip_7446fix.png\" target=\"_blank\" title=\"zulip_7446fix.png\"><img src=\"/user_uploads/2/3c/kxXkcMvLlk2RVtNTq-J2GDf0/zulip_7446fix.png\"></a></div><p>Thanks!</p>",
        "id": 609449,
        "sender_full_name": "Sourab",
        "timestamp": 1530950131
    },
    {
        "content": "<p>My 2 cents: Could we align the checkbox in with the textbox above it? Feels a bit like it’s floating at the moment. Looks good to me otherwise.</p>",
        "id": 609492,
        "sender_full_name": "Armaan Ahluwalia",
        "timestamp": 1530969532
    },
    {
        "content": "<p>Also perhaps 5 px more padding between textbox and checkbox.</p>",
        "id": 609493,
        "sender_full_name": "Armaan Ahluwalia",
        "timestamp": 1530969590
    },
    {
        "content": "<p><span class=\"user-mention\" data-user-id=\"5837\">@Armaan Ahluwalia</span> Does this work?</p>\n<p><a href=\"user_uploads/2/46/wKP9WrSLucxmf4L9GMnUwW58/pasted_image.png\" target=\"_blank\" title=\"user_uploads/2/46/wKP9WrSLucxmf4L9GMnUwW58/pasted_image.png\">pasted image</a></p>\n<div class=\"message_inline_image\"><a href=\"user_uploads/2/46/wKP9WrSLucxmf4L9GMnUwW58/pasted_image.png\" target=\"_blank\" title=\"pasted image\"><img src=\"user_uploads/2/46/wKP9WrSLucxmf4L9GMnUwW58/pasted_image.png\"></a></div>",
        "id": 609497,
        "sender_full_name": "Sourab",
        "timestamp": 1530970952
    },
    {
        "content": "<p>That looks better to me. Also just make sure the text is aligned to baseline. The text could be 1px lower relative to the checkbox IMO</p>",
        "id": 609498,
        "sender_full_name": "Armaan Ahluwalia",
        "timestamp": 1530971036
    },
    {
        "content": "<p>I'm trying to keep the design uniform w.r.t.  the streams checkboxes though...<br>\nis that a bad idea?</p>",
        "id": 609499,
        "sender_full_name": "Sourab",
        "timestamp": 1530971281
    },
    {
        "content": "<p>Not really that’s just how it looks to me <span class=\"emoji emoji-1f642\" title=\"simple smile\">:simple_smile:</span></p>",
        "id": 609501,
        "sender_full_name": "Armaan Ahluwalia",
        "timestamp": 1530971944
    },
    {
        "content": "<p>Cool thanks</p>",
        "id": 609503,
        "sender_full_name": "Sourab",
        "timestamp": 1530972465
    }
]