[
    {
        "content": "<p>Facing a issue where users that login with SAML for the first time are not auto-register. <br>\nThey see a page saying \"cant find account\", and they then have to click the register link.<br>\nIs this by design, or am I missing some setting?<br>\n(SAML + LDAP)</p>",
        "id": 1228100,
        "sender_full_name": "Ricardo Duarte",
        "timestamp": 1625781874
    },
    {
        "content": "<p><span class=\"user-mention\" data-user-id=\"10530\">@Ricardo Duarte</span> this feature doesn't exist yet, but I might merge it next.</p>",
        "id": 1228115,
        "sender_full_name": "Tim Abbott",
        "timestamp": 1625782407
    },
    {
        "content": "<p><a href=\"https://github.com/zulip/zulip/pull/16009\">https://github.com/zulip/zulip/pull/16009</a></p>",
        "id": 1228116,
        "sender_full_name": "Tim Abbott",
        "timestamp": 1625782411
    },
    {
        "content": "<p>OK, just merged that, and backported to the 4.x branch, so <span class=\"user-mention\" data-user-id=\"10530\">@Ricardo Duarte</span> you should be able to try it out with <code>upgrade-zulip-from-git 4.x</code>.</p>",
        "id": 1228122,
        "sender_full_name": "Tim Abbott",
        "timestamp": 1625782948
    },
    {
        "content": "<p>(Very convenient timing!)</p>",
        "id": 1228123,
        "sender_full_name": "Tim Abbott",
        "timestamp": 1625782964
    },
    {
        "content": "<p><span aria-label=\"smile\" class=\"emoji emoji-1f642\" role=\"img\" title=\"smile\">:smile:</span> will give it a try<br>\nthanks</p>",
        "id": 1228132,
        "sender_full_name": "Ricardo Duarte",
        "timestamp": 1625784231
    }
]