[
    {
        "content": "<p>Could someone please give me a stable commit so I can upgrade my server to it?</p>",
        "id": 620807,
        "sender_full_name": "Shayan Toqraee",
        "timestamp": 1532951462
    },
    {
        "content": "<p><span class=\"user-mention\" data-user-id=\"7\">@Tim Abbott</span></p>",
        "id": 620808,
        "sender_full_name": "Shayan Toqraee",
        "timestamp": 1532951485
    },
    {
        "content": "<p>Maybe :</p>\n<p>root@zulip:/etc/zulip# /home/zulip/deployments/current/scripts/upgrade-zulip-from-git master</p>",
        "id": 620862,
        "sender_full_name": "Pantoufle",
        "timestamp": 1532959569
    },
    {
        "content": "<p>I know how to do it, I want a stable commit. Sometimes master is not very suitable for production.</p>",
        "id": 620939,
        "sender_full_name": "Shayan Toqraee",
        "timestamp": 1532969661
    },
    {
        "content": "<p><span class=\"user-mention\" data-user-id=\"7\">@Tim Abbott</span> Do you have time to answer this?</p>",
        "id": 620944,
        "sender_full_name": "Shayan Toqraee",
        "timestamp": 1532970127
    },
    {
        "content": "<p><span class=\"user-mention\" data-user-id=\"1073\">@Shayan Toqraee</span> <a href=\"https://github.com/zulip/zulip/commit/e276006d8c35522475124878278fefba8e352ece\" target=\"_blank\" title=\"https://github.com/zulip/zulip/commit/e276006d8c35522475124878278fefba8e352ece\">e276006d8c35522475124878278fefba8e352ece</a> is a fine stable commit.</p>",
        "id": 620973,
        "sender_full_name": "Tim Abbott",
        "timestamp": 1532971042
    },
    {
        "content": "<p>Thanks a lot Tim!</p>",
        "id": 620974,
        "sender_full_name": "Shayan Toqraee",
        "timestamp": 1532971062
    }
]